Workbook
Name ListaInsumos: INSUMOS!$B$5:$B$67
Name ListaProductos: PRODUCTOS!$B$5:$B$104

Sheet INICIO
A1: 📊 CONTROL DE STOCK — Papelería
A3: ¿Cómo funciona?
A4: 1️⃣ INSUMOS → completá stock inicial, stock mínimo y costos (celdas amarillas).
A5: 2️⃣ PRODUCTOS → anotá cada producto que fabricás (ej: libreta A5, marcapáginas…).
A6: 3️⃣ RECETAS → por cada producto, listá qué insumos y cuánto lleva por unidad.
A7: 4️⃣ COMPRAS → cada vez que compres insumos, sumás una fila y el stock sube solo.
A8: 5️⃣ PRODUCCIÓN → cada vez que hagas productos, sumás una fila y los insumos se descuentan solos.
A9: 6️⃣ PERDIDAS → si un insumo se dañó, se imprimió mal o se perdió, anotalo y se descuenta del stock.
A10: 7️⃣ COSTOS → mirá cuánto cuesta fabricar cada producto y a cuánto conviene venderlo.
A11: 8️⃣ PRECIOS → guardá el precio de venta de cada producto y mirá el IVA y la ganancia real.
A12: 💡 Este panel te muestra qué insumos están bajos o agotados.
A13: Resumen
A14: Total insumos registrados | D14: =COUNTA(INSUMOS!B5:B67)
A15: Insumos SIN STOCK | D15: =COUNTIF(INSUMOS!J5:J67,"SIN STOCK")
A16: Insumos con BAJO STOCK | D16: =COUNTIF(INSUMOS!J5:J67,"BAJO STOCK")
A17: Insumos OK | D17: =COUNTIF(INSUMOS!J5:J67,"OK")
A18: Valor total en stock | D18: =SUM(INSUMOS!L5:L67)
A19: Valor perdido en errores/mermas | D19: =SUM(PERDIDAS!E5:E504)
A20: 🚨 Insumos que requieren atención
A21: Nombre | B21: Categoría | C21: Stock actual | D21: Stock mínimo | E21: Estado | F21: Notas
A22: =IFERROR(INDEX(INSUMOS!B:B,IFERROR(SMALL(IF((INSUMOS!$J$5:$J$67<>"OK")*(INSUMOS!$J$5:$J$67<>""),ROW(INSUMOS!$J$5:$J$67)),1),"")),"") | B22: =IFERROR(INDEX(INSUMOS!C:C,IFERROR(SMALL(IF((INSUMOS!$J$5:$J$67<>"OK")*(INSUMOS!$J$5:$J$67<>""),ROW(INSUMOS!$J$5:$J$67)),1),"")),"") | C22: =IFERROR(INDEX(INSUMOS!H:H,IFERROR(SMALL(IF((INSUMOS!$J$5:$J$67<>"OK")*(INSUMOS!$J$5:$J$67<>""),ROW(INSUMOS!$J$5:$J$67)),1),"")),"") | D22: =IFERROR(INDEX(INSUMOS!I:I,IFERROR(SMALL(IF((INSUMOS!$J$5:$J$67<>"OK")*(INSUMOS!$J$5:$J$67<>""),ROW(INSUMOS!$J$5:$J$67)),1),"")),"") | E22: =IFERROR(INDEX(INSUMOS!J:J,IFERROR(SMALL(IF((INSUMOS!$J$5:$J$67<>"OK")*(INSUMOS!$J$5:$J$67<>""),ROW(INSUMOS!$J$5:$J$67)),1),"")),"") | F22: =IFERROR(INDEX(INSUMOS!M:M,IFERROR(SMALL(IF((INSUMOS!$J$5:$J$67<>"OK")*(INSUMOS!$J$5:$J$67<>""),ROW(INSUMOS!$J$5:$J$67)),1),"")),"")
A23: =IFERROR(INDEX(INSUMOS!B:B,IFERROR(SMALL(IF((INSUMOS!$J$5:$J$67<>"OK")*(INSUMOS!$J$5:$J$67<>""),ROW(INSUMOS!$J$5:$J$67)),2),"")),"") | B23: =IFERROR(INDEX(INSUMOS!C:C,IFERROR(SMALL(IF((INSUMOS!$J$5:$J$67<>"OK")*(INSUMOS!$J$5:$J$67<>""),ROW(INSUMOS!$J$5:$J$67)),2),"")),"") | C23: =IFERROR(INDEX(INSUMOS!H:H,IFERROR(SMALL(IF((INSUMOS!$J$5:$J$67<>"OK")*(INSUMOS!$J$5:$J$67<>""),ROW(INSUMOS!$J$5:$J$67)),2),"")),"") | D23: =IFERROR(INDEX(INSUMOS!I:I,IFERROR(SMALL(IF((INSUMOS!$J$5:$J$67<>"OK")*(INSUMOS!$J$5:$J$67<>""),ROW(INSUMOS!$J$5:$J$67)),2),"")),"") | E23: =IFERROR(INDEX(INSUMOS!J:J,IFERROR(SMALL(IF((INSUMOS!$J$5:$J$67<>"OK")*(INSUMOS!$J$5:$J$67<>""),ROW(INSUMOS!$J$5:$J$67)),2),"")),"") | F23: =IFERROR(INDEX(INSUMOS!M:M,IFERROR(SMALL(IF((INSUMOS!$J$5:$J$67<>"OK")*(INSUMOS!$J$5:$J$67<>""),ROW(INSUMOS!$J$5:$J$67)),2),"")),"")
A24: =IFERROR(INDEX(INSUMOS!B:B,IFERROR(SMALL(IF((INSUMOS!$J$5:$J$67<>"OK")*(INSUMOS!$J$5:$J$67<>""),ROW(INSUMOS!$J$5:$J$67)),3),"")),"") | B24: =IFERROR(INDEX(INSUMOS!C:C,IFERROR(SMALL(IF((INSUMOS!$J$5:$J$67<>"OK")*(INSUMOS!$J$5:$J$67<>""),ROW(INSUMOS!$J$5:$J$67)),3),"")),"") | C24: =IFERROR(INDEX(INSUMOS!H:H,IFERROR(SMALL(IF((INSUMOS!$J$5:$J$67<>"OK")*(INSUMOS!$J$5:$J$67<>""),ROW(INSUMOS!$J$5:$J$67)),3),"")),"") | D24: =IFERROR(INDEX(INSUMOS!I:I,IFERROR(SMALL(IF((INSUMOS!$J$5:$J$67<>"OK")*(INSUMOS!$J$5:$J$67<>""),ROW(INSUMOS!$J$5:$J$67)),3),"")),"") | E24: =IFERROR(INDEX(INSUMOS!J:J,IFERROR(SMALL(IF((INSUMOS!$J$5:$J$67<>"OK")*(INSUMOS!$J$5:$J$67<>""),ROW(INSUMOS!$J$5:$J$67)),3),"")),"") | F24: =IFERROR(INDEX(INSUMOS!M:M,IFERROR(SMALL(IF((INSUMOS!$J$5:$J$67<>"OK")*(INSUMOS!$J$5:$J$67<>""),ROW(INSUMOS!$J$5:$J$67)),3),"")),"")
A25: =IFERROR(INDEX(INSUMOS!B:B,IFERROR(SMALL(IF((INSUMOS!$J$5:$J$67<>"OK")*(INSUMOS!$J$5:$J$67<>""),ROW(INSUMOS!$J$5:$J$67)),4),"")),"") | B25: =IFERROR(INDEX(INSUMOS!C:C,IFERROR(SMALL(IF((INSUMOS!$J$5:$J$67<>"OK")*(INSUMOS!$J$5:$J$67<>""),ROW(INSUMOS!$J$5:$J$67)),4),"")),"") | C25: =IFERROR(INDEX(INSUMOS!H:H,IFERROR(SMALL(IF((INSUMOS!$J$5:$J$67<>"OK")*(INSUMOS!$J$5:$J$67<>""),ROW(INSUMOS!$J$5:$J$67)),4),"")),"") | D25: =IFERROR(INDEX(INSUMOS!I:I,IFERROR(SMALL(IF((INSUMOS!$J$5:$J$67<>"OK")*(INSUMOS!$J$5:$J$67<>""),ROW(INSUMOS!$J$5:$J$67)),4),"")),"") | E25: =IFERROR(INDEX(INSUMOS!J:J,IFERROR(SMALL(IF((INSUMOS!$J$5:$J$67<>"OK")*(INSUMOS!$J$5:$J$67<>""),ROW(INSUMOS!$J$5:$J$67)),4),"")),"") | F25: =IFERROR(INDEX(INSUMOS!M:M,IFERROR(SMALL(IF((INSUMOS!$J$5:$J$67<>"OK")*(INSUMOS!$J$5:$J$67<>""),ROW(INSUMOS!$J$5:$J$67)),4),"")),"")
A26: =IFERROR(INDEX(INSUMOS!B:B,IFERROR(SMALL(IF((INSUMOS!$J$5:$J$67<>"OK")*(INSUMOS!$J$5:$J$67<>""),ROW(INSUMOS!$J$5:$J$67)),5),"")),"") | B26: =IFERROR(INDEX(INSUMOS!C:C,IFERROR(SMALL(IF((INSUMOS!$J$5:$J$67<>"OK")*(INSUMOS!$J$5:$J$67<>""),ROW(INSUMOS!$J$5:$J$67)),5),"")),"") | C26: =IFERROR(INDEX(INSUMOS!H:H,IFERROR(SMALL(IF((INSUMOS!$J$5:$J$67<>"OK")*(INSUMOS!$J$5:$J$67<>""),ROW(INSUMOS!$J$5:$J$67)),5),"")),"") | D26: =IFERROR(INDEX(INSUMOS!I:I,IFERROR(SMALL(IF((INSUMOS!$J$5:$J$67<>"OK")*(INSUMOS!$J$5:$J$67<>""),ROW(INSUMOS!$J$5:$J$67)),5),"")),"") | E26: =IFERROR(INDEX(INSUMOS!J:J,IFERROR(SMALL(IF((INSUMOS!$J$5:$J$67<>"OK")*(INSUMOS!$J$5:$J$67<>""),ROW(INSUMOS!$J$5:$J$67)),5),"")),"") | F26: =IFERROR(INDEX(INSUMOS!M:M,IFERROR(SMALL(IF((INSUMOS!$J$5:$J$67<>"OK")*(INSUMOS!$J$5:$J$67<>""),ROW(INSUMOS!$J$5:$J$67)),5),"")),"")
A27: =IFERROR(INDEX(INSUMOS!B:B,IFERROR(SMALL(IF((INSUMOS!$J$5:$J$67<>"OK")*(INSUMOS!$J$5:$J$67<>""),ROW(INSUMOS!$J$5:$J$67)),6),"")),"") | B27: =IFERROR(INDEX(INSUMOS!C:C,IFERROR(SMALL(IF((INSUMOS!$J$5:$J$67<>"OK")*(INSUMOS!$J$5:$J$67<>""),ROW(INSUMOS!$J$5:$J$67)),6),"")),"") | C27: =IFERROR(INDEX(INSUMOS!H:H,IFERROR(SMALL(IF((INSUMOS!$J$5:$J$67<>"OK")*(INSUMOS!$J$5:$J$67<>""),ROW(INSUMOS!$J$5:$J$67)),6),"")),"") | D27: =IFERROR(INDEX(INSUMOS!I:I,IFERROR(SMALL(IF((INSUMOS!$J$5:$J$67<>"OK")*(INSUMOS!$J$5:$J$67<>""),ROW(INSUMOS!$J$5:$J$67)),6),"")),"") | E27: =IFERROR(INDEX(INSUMOS!J:J,IFERROR(SMALL(IF((INSUMOS!$J$5:$J$67<>"OK")*(INSUMOS!$J$5:$J$67<>""),ROW(INSUMOS!$J$5:$J$67)),6),"")),"") | F27: =IFERROR(INDEX(INSUMOS!M:M,IFERROR(SMALL(IF((INSUMOS!$J$5:$J$67<>"OK")*(INSUMOS!$J$5:$J$67<>""),ROW(INSUMOS!$J$5:$J$67)),6),"")),"")
A28: =IFERROR(INDEX(INSUMOS!B:B,IFERROR(SMALL(IF((INSUMOS!$J$5:$J$67<>"OK")*(INSUMOS!$J$5:$J$67<>""),ROW(INSUMOS!$J$5:$J$67)),7),"")),"") | B28: =IFERROR(INDEX(INSUMOS!C:C,IFERROR(SMALL(IF((INSUMOS!$J$5:$J$67<>"OK")*(INSUMOS!$J$5:$J$67<>""),ROW(INSUMOS!$J$5:$J$67)),7),"")),"") | C28: =IFERROR(INDEX(INSUMOS!H:H,IFERROR(SMALL(IF((INSUMOS!$J$5:$J$67<>"OK")*(INSUMOS!$J$5:$J$67<>""),ROW(INSUMOS!$J$5:$J$67)),7),"")),"") | D28: =IFERROR(INDEX(INSUMOS!I:I,IFERROR(SMALL(IF((INSUMOS!$J$5:$J$67<>"OK")*(INSUMOS!$J$5:$J$67<>""),ROW(INSUMOS!$J$5:$J$67)),7),"")),"") | E28: =IFERROR(INDEX(INSUMOS!J:J,IFERROR(SMALL(IF((INSUMOS!$J$5:$J$67<>"OK")*(INSUMOS!$J$5:$J$67<>""),ROW(INSUMOS!$J$5:$J$67)),7),"")),"") | F28: =IFERROR(INDEX(INSUMOS!M:M,IFERROR(SMALL(IF((INSUMOS!$J$5:$J$67<>"OK")*(INSUMOS!$J$5:$J$67<>""),ROW(INSUMOS!$J$5:$J$67)),7),"")),"")
A29: =IFERROR(INDEX(INSUMOS!B:B,IFERROR(SMALL(IF((INSUMOS!$J$5:$J$67<>"OK")*(INSUMOS!$J$5:$J$67<>""),ROW(INSUMOS!$J$5:$J$67)),8),"")),"") | B29: =IFERROR(INDEX(INSUMOS!C:C,IFERROR(SMALL(IF((INSUMOS!$J$5:$J$67<>"OK")*(INSUMOS!$J$5:$J$67<>""),ROW(INSUMOS!$J$5:$J$67)),8),"")),"") | C29: =IFERROR(INDEX(INSUMOS!H:H,IFERROR(SMALL(IF((INSUMOS!$J$5:$J$67<>"OK")*(INSUMOS!$J$5:$J$67<>""),ROW(INSUMOS!$J$5:$J$67)),8),"")),"") | D29: =IFERROR(INDEX(INSUMOS!I:I,IFERROR(SMALL(IF((INSUMOS!$J$5:$J$67<>"OK")*(INSUMOS!$J$5:$J$67<>""),ROW(INSUMOS!$J$5:$J$67)),8),"")),"") | E29: =IFERROR(INDEX(INSUMOS!J:J,IFERROR(SMALL(IF((INSUMOS!$J$5:$J$67<>"OK")*(INSUMOS!$J$5:$J$67<>""),ROW(INSUMOS!$J$5:$J$67)),8),"")),"") | F29: =IFERROR(INDEX(INSUMOS!M:M,IFERROR(SMALL(IF((INSUMOS!$J$5:$J$67<>"OK")*(INSUMOS!$J$5:$J$67<>""),ROW(INSUMOS!$J$5:$J$67)),8),"")),"")
A30: =IFERROR(INDEX(INSUMOS!B:B,IFERROR(SMALL(IF((INSUMOS!$J$5:$J$67<>"OK")*(INSUMOS!$J$5:$J$67<>""),ROW(INSUMOS!$J$5:$J$67)),9),"")),"") | B30: =IFERROR(INDEX(INSUMOS!C:C,IFERROR(SMALL(IF((INSUMOS!$J$5:$J$67<>"OK")*(INSUMOS!$J$5:$J$67<>""),ROW(INSUMOS!$J$5:$J$67)),9),"")),"") | C30: =IFERROR(INDEX(INSUMOS!H:H,IFERROR(SMALL(IF((INSUMOS!$J$5:$J$67<>"OK")*(INSUMOS!$J$5:$J$67<>""),ROW(INSUMOS!$J$5:$J$67)),9),"")),"") | D30: =IFERROR(INDEX(INSUMOS!I:I,IFERROR(SMALL(IF((INSUMOS!$J$5:$J$67<>"OK")*(INSUMOS!$J$5:$J$67<>""),ROW(INSUMOS!$J$5:$J$67)),9),"")),"") | E30: =IFERROR(INDEX(INSUMOS!J:J,IFERROR(SMALL(IF((INSUMOS!$J$5:$J$67<>"OK")*(INSUMOS!$J$5:$J$67<>""),ROW(INSUMOS!$J$5:$J$67)),9),"")),"") | F30: =IFERROR(INDEX(INSUMOS!M:M,IFERROR(SMALL(IF((INSUMOS!$J$5:$J$67<>"OK")*(INSUMOS!$J$5:$J$67<>""),ROW(INSUMOS!$J$5:$J$67)),9),"")),"")
A31: =IFERROR(INDEX(INSUMOS!B:B,IFERROR(SMALL(IF((INSUMOS!$J$5:$J$67<>"OK")*(INSUMOS!$J$5:$J$67<>""),ROW(INSUMOS!$J$5:$J$67)),10),"")),"") | B31: =IFERROR(INDEX(INSUMOS!C:C,IFERROR(SMALL(IF((INSUMOS!$J$5:$J$67<>"OK")*(INSUMOS!$J$5:$J$67<>""),ROW(INSUMOS!$J$5:$J$67)),10),"")),"") | C31: =IFERROR(INDEX(INSUMOS!H:H,IFERROR(SMALL(IF((INSUMOS!$J$5:$J$67<>"OK")*(INSUMOS!$J$5:$J$67<>""),ROW(INSUMOS!$J$5:$J$67)),10),"")),"") | D31: =IFERROR(INDEX(INSUMOS!I:I,IFERROR(SMALL(IF((INSUMOS!$J$5:$J$67<>"OK")*(INSUMOS!$J$5:$J$67<>""),ROW(INSUMOS!$J$5:$J$67)),10),"")),"") | E31: =IFERROR(INDEX(INSUMOS!J:J,IFERROR(SMALL(IF((INSUMOS!$J$5:$J$67<>"OK")*(INSUMOS!$J$5:$J$67<>""),ROW(INSUMOS!$J$5:$J$67)),10),"")),"") | F31: =IFERROR(INDEX(INSUMOS!M:M,IFERROR(SMALL(IF((INSUMOS!$J$5:$J$67<>"OK")*(INSUMOS!$J$5:$J$67<>""),ROW(INSUMOS!$J$5:$J$67)),10),"")),"")
A32: =IFERROR(INDEX(INSUMOS!B:B,IFERROR(SMALL(IF((INSUMOS!$J$5:$J$67<>"OK")*(INSUMOS!$J$5:$J$67<>""),ROW(INSUMOS!$J$5:$J$67)),11),"")),"") | B32: =IFERROR(INDEX(INSUMOS!C:C,IFERROR(SMALL(IF((INSUMOS!$J$5:$J$67<>"OK")*(INSUMOS!$J$5:$J$67<>""),ROW(INSUMOS!$J$5:$J$67)),11),"")),"") | C32: =IFERROR(INDEX(INSUMOS!H:H,IFERROR(SMALL(IF((INSUMOS!$J$5:$J$67<>"OK")*(INSUMOS!$J$5:$J$67<>""),ROW(INSUMOS!$J$5:$J$67)),11),"")),"") | D32: =IFERROR(INDEX(INSUMOS!I:I,IFERROR(SMALL(IF((INSUMOS!$J$5:$J$67<>"OK")*(INSUMOS!$J$5:$J$67<>""),ROW(INSUMOS!$J$5:$J$67)),11),"")),"") | E32: =IFERROR(INDEX(INSUMOS!J:J,IFERROR(SMALL(IF((INSUMOS!$J$5:$J$67<>"OK")*(INSUMOS!$J$5:$J$67<>""),ROW(INSUMOS!$J$5:$J$67)),11),"")),"") | F32: =IFERROR(INDEX(INSUMOS!M:M,IFERROR(SMALL(IF((INSUMOS!$J$5:$J$67<>"OK")*(INSUMOS!$J$5:$J$67<>""),ROW(INSUMOS!$J$5:$J$67)),11),"")),"")
A33: =IFERROR(INDEX(INSUMOS!B:B,IFERROR(SMALL(IF((INSUMOS!$J$5:$J$67<>"OK")*(INSUMOS!$J$5:$J$67<>""),ROW(INSUMOS!$J$5:$J$67)),12),"")),"") | B33: =IFERROR(INDEX(INSUMOS!C:C,IFERROR(SMALL(IF((INSUMOS!$J$5:$J$67<>"OK")*(INSUMOS!$J$5:$J$67<>""),ROW(INSUMOS!$J$5:$J$67)),12),"")),"") | C33: =IFERROR(INDEX(INSUMOS!H:H,IFERROR(SMALL(IF((INSUMOS!$J$5:$J$67<>"OK")*(INSUMOS!$J$5:$J$67<>""),ROW(INSUMOS!$J$5:$J$67)),12),"")),"") | D33: =IFERROR(INDEX(INSUMOS!I:I,IFERROR(SMALL(IF((INSUMOS!$J$5:$J$67<>"OK")*(INSUMOS!$J$5:$J$67<>""),ROW(INSUMOS!$J$5:$J$67)),12),"")),"") | E33: =IFERROR(INDEX(INSUMOS!J:J,IFERROR(SMALL(IF((INSUMOS!$J$5:$J$67<>"OK")*(INSUMOS!$J$5:$J$67<>""),ROW(INSUMOS!$J$5:$J$67)),12),"")),"") | F33: =IFERROR(INDEX(INSUMOS!M:M,IFERROR(SMALL(IF((INSUMOS!$J$5:$J$67<>"OK")*(INSUMOS!$J$5:$J$67<>""),ROW(INSUMOS!$J$5:$J$67)),12),"")),"")
A34: =IFERROR(INDEX(INSUMOS!B:B,IFERROR(SMALL(IF((INSUMOS!$J$5:$J$67<>"OK")*(INSUMOS!$J$5:$J$67<>""),ROW(INSUMOS!$J$5:$J$67)),13),"")),"") | B34: =IFERROR(INDEX(INSUMOS!C:C,IFERROR(SMALL(IF((INSUMOS!$J$5:$J$67<>"OK")*(INSUMOS!$J$5:$J$67<>""),ROW(INSUMOS!$J$5:$J$67)),13),"")),"") | C34: =IFERROR(INDEX(INSUMOS!H:H,IFERROR(SMALL(IF((INSUMOS!$J$5:$J$67<>"OK")*(INSUMOS!$J$5:$J$67<>""),ROW(INSUMOS!$J$5:$J$67)),13),"")),"") | D34: =IFERROR(INDEX(INSUMOS!I:I,IFERROR(SMALL(IF((INSUMOS!$J$5:$J$67<>"OK")*(INSUMOS!$J$5:$J$67<>""),ROW(INSUMOS!$J$5:$J$67)),13),"")),"") | E34: =IFERROR(INDEX(INSUMOS!J:J,IFERROR(SMALL(IF((INSUMOS!$J$5:$J$67<>"OK")*(INSUMOS!$J$5:$J$67<>""),ROW(INSUMOS!$J$5:$J$67)),13),"")),"") | F34: =IFERROR(INDEX(INSUMOS!M:M,IFERROR(SMALL(IF((INSUMOS!$J$5:$J$67<>"OK")*(INSUMOS!$J$5:$J$67<>""),ROW(INSUMOS!$J$5:$J$67)),13),"")),"")
A35: =IFERROR(INDEX(INSUMOS!B:B,IFERROR(SMALL(IF((INSUMOS!$J$5:$J$67<>"OK")*(INSUMOS!$J$5:$J$67<>""),ROW(INSUMOS!$J$5:$J$67)),14),"")),"") | B35: =IFERROR(INDEX(INSUMOS!C:C,IFERROR(SMALL(IF((INSUMOS!$J$5:$J$67<>"OK")*(INSUMOS!$J$5:$J$67<>""),ROW(INSUMOS!$J$5:$J$67)),14),"")),"") | C35: =IFERROR(INDEX(INSUMOS!H:H,IFERROR(SMALL(IF((INSUMOS!$J$5:$J$67<>"OK")*(INSUMOS!$J$5:$J$67<>""),ROW(INSUMOS!$J$5:$J$67)),14),"")),"") | D35: =IFERROR(INDEX(INSUMOS!I:I,IFERROR(SMALL(IF((INSUMOS!$J$5:$J$67<>"OK")*(INSUMOS!$J$5:$J$67<>""),ROW(INSUMOS!$J$5:$J$67)),14),"")),"") | E35: =IFERROR(INDEX(INSUMOS!J:J,IFERROR(SMALL(IF((INSUMOS!$J$5:$J$67<>"OK")*(INSUMOS!$J$5:$J$67<>""),ROW(INSUMOS!$J$5:$J$67)),14),"")),"") | F35: =IFERROR(INDEX(INSUMOS!M:M,IFERROR(SMALL(IF((INSUMOS!$J$5:$J$67<>"OK")*(INSUMOS!$J$5:$J$67<>""),ROW(INSUMOS!$J$5:$J$67)),14),"")),"")
A36: =IFERROR(INDEX(INSUMOS!B:B,IFERROR(SMALL(IF((INSUMOS!$J$5:$J$67<>"OK")*(INSUMOS!$J$5:$J$67<>""),ROW(INSUMOS!$J$5:$J$67)),15),"")),"") | B36: =IFERROR(INDEX(INSUMOS!C:C,IFERROR(SMALL(IF((INSUMOS!$J$5:$J$67<>"OK")*(INSUMOS!$J$5:$J$67<>""),ROW(INSUMOS!$J$5:$J$67)),15),"")),"") | C36: =IFERROR(INDEX(INSUMOS!H:H,IFERROR(SMALL(IF((INSUMOS!$J$5:$J$67<>"OK")*(INSUMOS!$J$5:$J$67<>""),ROW(INSUMOS!$J$5:$J$67)),15),"")),"") | D36: =IFERROR(INDEX(INSUMOS!I:I,IFERROR(SMALL(IF((INSUMOS!$J$5:$J$67<>"OK")*(INSUMOS!$J$5:$J$67<>""),ROW(INSUMOS!$J$5:$J$67)),15),"")),"") | E36: =IFERROR(INDEX(INSUMOS!J:J,IFERROR(SMALL(IF((INSUMOS!$J$5:$J$67<>"OK")*(INSUMOS!$J$5:$J$67<>""),ROW(INSUMOS!$J$5:$J$67)),15),"")),"") | F36: =IFERROR(INDEX(INSUMOS!M:M,IFERROR(SMALL(IF((INSUMOS!$J$5:$J$67<>"OK")*(INSUMOS!$J$5:$J$67<>""),ROW(INSUMOS!$J$5:$J$67)),15),"")),"")
A37: =IFERROR(INDEX(INSUMOS!B:B,IFERROR(SMALL(IF((INSUMOS!$J$5:$J$67<>"OK")*(INSUMOS!$J$5:$J$67<>""),ROW(INSUMOS!$J$5:$J$67)),16),"")),"") | B37: =IFERROR(INDEX(INSUMOS!C:C,IFERROR(SMALL(IF((INSUMOS!$J$5:$J$67<>"OK")*(INSUMOS!$J$5:$J$67<>""),ROW(INSUMOS!$J$5:$J$67)),16),"")),"") | C37: =IFERROR(INDEX(INSUMOS!H:H,IFERROR(SMALL(IF((INSUMOS!$J$5:$J$67<>"OK")*(INSUMOS!$J$5:$J$67<>""),ROW(INSUMOS!$J$5:$J$67)),16),"")),"") | D37: =IFERROR(INDEX(INSUMOS!I:I,IFERROR(SMALL(IF((INSUMOS!$J$5:$J$67<>"OK")*(INSUMOS!$J$5:$J$67<>""),ROW(INSUMOS!$J$5:$J$67)),16),"")),"") | E37: =IFERROR(INDEX(INSUMOS!J:J,IFERROR(SMALL(IF((INSUMOS!$J$5:$J$67<>"OK")*(INSUMOS!$J$5:$J$67<>""),ROW(INSUMOS!$J$5:$J$67)),16),"")),"") | F37: =IFERROR(INDEX(INSUMOS!M:M,IFERROR(SMALL(IF((INSUMOS!$J$5:$J$67<>"OK")*(INSUMOS!$J$5:$J$67<>""),ROW(INSUMOS!$J$5:$J$67)),16),"")),"")
A38: =IFERROR(INDEX(INSUMOS!B:B,IFERROR(SMALL(IF((INSUMOS!$J$5:$J$67<>"OK")*(INSUMOS!$J$5:$J$67<>""),ROW(INSUMOS!$J$5:$J$67)),17),"")),"") | B38: =IFERROR(INDEX(INSUMOS!C:C,IFERROR(SMALL(IF((INSUMOS!$J$5:$J$67<>"OK")*(INSUMOS!$J$5:$J$67<>""),ROW(INSUMOS!$J$5:$J$67)),17),"")),"") | C38: =IFERROR(INDEX(INSUMOS!H:H,IFERROR(SMALL(IF((INSUMOS!$J$5:$J$67<>"OK")*(INSUMOS!$J$5:$J$67<>""),ROW(INSUMOS!$J$5:$J$67)),17),"")),"") | D38: =IFERROR(INDEX(INSUMOS!I:I,IFERROR(SMALL(IF((INSUMOS!$J$5:$J$67<>"OK")*(INSUMOS!$J$5:$J$67<>""),ROW(INSUMOS!$J$5:$J$67)),17),"")),"") | E38: =IFERROR(INDEX(INSUMOS!J:J,IFERROR(SMALL(IF((INSUMOS!$J$5:$J$67<>"OK")*(INSUMOS!$J$5:$J$67<>""),ROW(INSUMOS!$J$5:$J$67)),17),"")),"") | F38: =IFERROR(INDEX(INSUMOS!M:M,IFERROR(SMALL(IF((INSUMOS!$J$5:$J$67<>"OK")*(INSUMOS!$J$5:$J$67<>""),ROW(INSUMOS!$J$5:$J$67)),17),"")),"")
A39: =IFERROR(INDEX(INSUMOS!B:B,IFERROR(SMALL(IF((INSUMOS!$J$5:$J$67<>"OK")*(INSUMOS!$J$5:$J$67<>""),ROW(INSUMOS!$J$5:$J$67)),18),"")),"") | B39: =IFERROR(INDEX(INSUMOS!C:C,IFERROR(SMALL(IF((INSUMOS!$J$5:$J$67<>"OK")*(INSUMOS!$J$5:$J$67<>""),ROW(INSUMOS!$J$5:$J$67)),18),"")),"") | C39: =IFERROR(INDEX(INSUMOS!H:H,IFERROR(SMALL(IF((INSUMOS!$J$5:$J$67<>"OK")*(INSUMOS!$J$5:$J$67<>""),ROW(INSUMOS!$J$5:$J$67)),18),"")),"") | D39: =IFERROR(INDEX(INSUMOS!I:I,IFERROR(SMALL(IF((INSUMOS!$J$5:$J$67<>"OK")*(INSUMOS!$J$5:$J$67<>""),ROW(INSUMOS!$J$5:$J$67)),18),"")),"") | E39: =IFERROR(INDEX(INSUMOS!J:J,IFERROR(SMALL(IF((INSUMOS!$J$5:$J$67<>"OK")*(INSUMOS!$J$5:$J$67<>""),ROW(INSUMOS!$J$5:$J$67)),18),"")),"") | F39: =IFERROR(INDEX(INSUMOS!M:M,IFERROR(SMALL(IF((INSUMOS!$J$5:$J$67<>"OK")*(INSUMOS!$J$5:$J$67<>""),ROW(INSUMOS!$J$5:$J$67)),18),"")),"")
A40: =IFERROR(INDEX(INSUMOS!B:B,IFERROR(SMALL(IF((INSUMOS!$J$5:$J$67<>"OK")*(INSUMOS!$J$5:$J$67<>""),ROW(INSUMOS!$J$5:$J$67)),19),"")),"") | B40: =IFERROR(INDEX(INSUMOS!C:C,IFERROR(SMALL(IF((INSUMOS!$J$5:$J$67<>"OK")*(INSUMOS!$J$5:$J$67<>""),ROW(INSUMOS!$J$5:$J$67)),19),"")),"") | C40: =IFERROR(INDEX(INSUMOS!H:H,IFERROR(SMALL(IF((INSUMOS!$J$5:$J$67<>"OK")*(INSUMOS!$J$5:$J$67<>""),ROW(INSUMOS!$J$5:$J$67)),19),"")),"") | D40: =IFERROR(INDEX(INSUMOS!I:I,IFERROR(SMALL(IF((INSUMOS!$J$5:$J$67<>"OK")*(INSUMOS!$J$5:$J$67<>""),ROW(INSUMOS!$J$5:$J$67)),19),"")),"") | E40: =IFERROR(INDEX(INSUMOS!J:J,IFERROR(SMALL(IF((INSUMOS!$J$5:$J$67<>"OK")*(INSUMOS!$J$5:$J$67<>""),ROW(INSUMOS!$J$5:$J$67)),19),"")),"") | F40: =IFERROR(INDEX(INSUMOS!M:M,IFERROR(SMALL(IF((INSUMOS!$J$5:$J$67<>"OK")*(INSUMOS!$J$5:$J$67<>""),ROW(INSUMOS!$J$5:$J$67)),19),"")),"")
A41: =IFERROR(INDEX(INSUMOS!B:B,IFERROR(SMALL(IF((INSUMOS!$J$5:$J$67<>"OK")*(INSUMOS!$J$5:$J$67<>""),ROW(INSUMOS!$J$5:$J$67)),20),"")),"") | B41: =IFERROR(INDEX(INSUMOS!C:C,IFERROR(SMALL(IF((INSUMOS!$J$5:$J$67<>"OK")*(INSUMOS!$J$5:$J$67<>""),ROW(INSUMOS!$J$5:$J$67)),20),"")),"") | C41: =IFERROR(INDEX(INSUMOS!H:H,IFERROR(SMALL(IF((INSUMOS!$J$5:$J$67<>"OK")*(INSUMOS!$J$5:$J$67<>""),ROW(INSUMOS!$J$5:$J$67)),20),"")),"") | D41: =IFERROR(INDEX(INSUMOS!I:I,IFERROR(SMALL(IF((INSUMOS!$J$5:$J$67<>"OK")*(INSUMOS!$J$5:$J$67<>""),ROW(INSUMOS!$J$5:$J$67)),20),"")),"") | E41: =IFERROR(INDEX(INSUMOS!J:J,IFERROR(SMALL(IF((INSUMOS!$J$5:$J$67<>"OK")*(INSUMOS!$J$5:$J$67<>""),ROW(INSUMOS!$J$5:$J$67)),20),"")),"") | F41: =IFERROR(INDEX(INSUMOS!M:M,IFERROR(SMALL(IF((INSUMOS!$J$5:$J$67<>"OK")*(INSUMOS!$J$5:$J$67<>""),ROW(INSUMOS!$J$5:$J$67)),20),"")),"")
A42: =IFERROR(INDEX(INSUMOS!B:B,IFERROR(SMALL(IF((INSUMOS!$J$5:$J$67<>"OK")*(INSUMOS!$J$5:$J$67<>""),ROW(INSUMOS!$J$5:$J$67)),21),"")),"") | B42: =IFERROR(INDEX(INSUMOS!C:C,IFERROR(SMALL(IF((INSUMOS!$J$5:$J$67<>"OK")*(INSUMOS!$J$5:$J$67<>""),ROW(INSUMOS!$J$5:$J$67)),21),"")),"") | C42: =IFERROR(INDEX(INSUMOS!H:H,IFERROR(SMALL(IF((INSUMOS!$J$5:$J$67<>"OK")*(INSUMOS!$J$5:$J$67<>""),ROW(INSUMOS!$J$5:$J$67)),21),"")),"") | D42: =IFERROR(INDEX(INSUMOS!I:I,IFERROR(SMALL(IF((INSUMOS!$J$5:$J$67<>"OK")*(INSUMOS!$J$5:$J$67<>""),ROW(INSUMOS!$J$5:$J$67)),21),"")),"") | E42: =IFERROR(INDEX(INSUMOS!J:J,IFERROR(SMALL(IF((INSUMOS!$J$5:$J$67<>"OK")*(INSUMOS!$J$5:$J$67<>""),ROW(INSUMOS!$J$5:$J$67)),21),"")),"") | F42: =IFERROR(INDEX(INSUMOS!M:M,IFERROR(SMALL(IF((INSUMOS!$J$5:$J$67<>"OK")*(INSUMOS!$J$5:$J$67<>""),ROW(INSUMOS!$J$5:$J$67)),21),"")),"")
A43: =IFERROR(INDEX(INSUMOS!B:B,IFERROR(SMALL(IF((INSUMOS!$J$5:$J$67<>"OK")*(INSUMOS!$J$5:$J$67<>""),ROW(INSUMOS!$J$5:$J$67)),22),"")),"") | B43: =IFERROR(INDEX(INSUMOS!C:C,IFERROR(SMALL(IF((INSUMOS!$J$5:$J$67<>"OK")*(INSUMOS!$J$5:$J$67<>""),ROW(INSUMOS!$J$5:$J$67)),22),"")),"") | C43: =IFERROR(INDEX(INSUMOS!H:H,IFERROR(SMALL(IF((INSUMOS!$J$5:$J$67<>"OK")*(INSUMOS!$J$5:$J$67<>""),ROW(INSUMOS!$J$5:$J$67)),22),"")),"") | D43: =IFERROR(INDEX(INSUMOS!I:I,IFERROR(SMALL(IF((INSUMOS!$J$5:$J$67<>"OK")*(INSUMOS!$J$5:$J$67<>""),ROW(INSUMOS!$J$5:$J$67)),22),"")),"") | E43: =IFERROR(INDEX(INSUMOS!J:J,IFERROR(SMALL(IF((INSUMOS!$J$5:$J$67<>"OK")*(INSUMOS!$J$5:$J$67<>""),ROW(INSUMOS!$J$5:$J$67)),22),"")),"") | F43: =IFERROR(INDEX(INSUMOS!M:M,IFERROR(SMALL(IF((INSUMOS!$J$5:$J$67<>"OK")*(INSUMOS!$J$5:$J$67<>""),ROW(INSUMOS!$J$5:$J$67)),22),"")),"")
A44: =IFERROR(INDEX(INSUMOS!B:B,IFERROR(SMALL(IF((INSUMOS!$J$5:$J$67<>"OK")*(INSUMOS!$J$5:$J$67<>""),ROW(INSUMOS!$J$5:$J$67)),23),"")),"") | B44: =IFERROR(INDEX(INSUMOS!C:C,IFERROR(SMALL(IF((INSUMOS!$J$5:$J$67<>"OK")*(INSUMOS!$J$5:$J$67<>""),ROW(INSUMOS!$J$5:$J$67)),23),"")),"") | C44: =IFERROR(INDEX(INSUMOS!H:H,IFERROR(SMALL(IF((INSUMOS!$J$5:$J$67<>"OK")*(INSUMOS!$J$5:$J$67<>""),ROW(INSUMOS!$J$5:$J$67)),23),"")),"") | D44: =IFERROR(INDEX(INSUMOS!I:I,IFERROR(SMALL(IF((INSUMOS!$J$5:$J$67<>"OK")*(INSUMOS!$J$5:$J$67<>""),ROW(INSUMOS!$J$5:$J$67)),23),"")),"") | E44: =IFERROR(INDEX(INSUMOS!J:J,IFERROR(SMALL(IF((INSUMOS!$J$5:$J$67<>"OK")*(INSUMOS!$J$5:$J$67<>""),ROW(INSUMOS!$J$5:$J$67)),23),"")),"") | F44: =IFERROR(INDEX(INSUMOS!M:M,IFERROR(SMALL(IF((INSUMOS!$J$5:$J$67<>"OK")*(INSUMOS!$J$5:$J$67<>""),ROW(INSUMOS!$J$5:$J$67)),23),"")),"")
A45: =IFERROR(INDEX(INSUMOS!B:B,IFERROR(SMALL(IF((INSUMOS!$J$5:$J$67<>"OK")*(INSUMOS!$J$5:$J$67<>""),ROW(INSUMOS!$J$5:$J$67)),24),"")),"") | B45: =IFERROR(INDEX(INSUMOS!C:C,IFERROR(SMALL(IF((INSUMOS!$J$5:$J$67<>"OK")*(INSUMOS!$J$5:$J$67<>""),ROW(INSUMOS!$J$5:$J$67)),24),"")),"") | C45: =IFERROR(INDEX(INSUMOS!H:H,IFERROR(SMALL(IF((INSUMOS!$J$5:$J$67<>"OK")*(INSUMOS!$J$5:$J$67<>""),ROW(INSUMOS!$J$5:$J$67)),24),"")),"") | D45: =IFERROR(INDEX(INSUMOS!I:I,IFERROR(SMALL(IF((INSUMOS!$J$5:$J$67<>"OK")*(INSUMOS!$J$5:$J$67<>""),ROW(INSUMOS!$J$5:$J$67)),24),"")),"") | E45: =IFERROR(INDEX(INSUMOS!J:J,IFERROR(SMALL(IF((INSUMOS!$J$5:$J$67<>"OK")*(INSUMOS!$J$5:$J$67<>""),ROW(INSUMOS!$J$5:$J$67)),24),"")),"") | F45: =IFERROR(INDEX(INSUMOS!M:M,IFERROR(SMALL(IF((INSUMOS!$J$5:$J$67<>"OK")*(INSUMOS!$J$5:$J$67<>""),ROW(INSUMOS!$J$5:$J$67)),24),"")),"")
A46: =IFERROR(INDEX(INSUMOS!B:B,IFERROR(SMALL(IF((INSUMOS!$J$5:$J$67<>"OK")*(INSUMOS!$J$5:$J$67<>""),ROW(INSUMOS!$J$5:$J$67)),25),"")),"") | B46: =IFERROR(INDEX(INSUMOS!C:C,IFERROR(SMALL(IF((INSUMOS!$J$5:$J$67<>"OK")*(INSUMOS!$J$5:$J$67<>""),ROW(INSUMOS!$J$5:$J$67)),25),"")),"") | C46: =IFERROR(INDEX(INSUMOS!H:H,IFERROR(SMALL(IF((INSUMOS!$J$5:$J$67<>"OK")*(INSUMOS!$J$5:$J$67<>""),ROW(INSUMOS!$J$5:$J$67)),25),"")),"") | D46: =IFERROR(INDEX(INSUMOS!I:I,IFERROR(SMALL(IF((INSUMOS!$J$5:$J$67<>"OK")*(INSUMOS!$J$5:$J$67<>""),ROW(INSUMOS!$J$5:$J$67)),25),"")),"") | E46: =IFERROR(INDEX(INSUMOS!J:J,IFERROR(SMALL(IF((INSUMOS!$J$5:$J$67<>"OK")*(INSUMOS!$J$5:$J$67<>""),ROW(INSUMOS!$J$5:$J$67)),25),"")),"") | F46: =IFERROR(INDEX(INSUMOS!M:M,IFERROR(SMALL(IF((INSUMOS!$J$5:$J$67<>"OK")*(INSUMOS!$J$5:$J$67<>""),ROW(INSUMOS!$J$5:$J$67)),25),"")),"")
A47: =IFERROR(INDEX(INSUMOS!B:B,IFERROR(SMALL(IF((INSUMOS!$J$5:$J$67<>"OK")*(INSUMOS!$J$5:$J$67<>""),ROW(INSUMOS!$J$5:$J$67)),26),"")),"") | B47: =IFERROR(INDEX(INSUMOS!C:C,IFERROR(SMALL(IF((INSUMOS!$J$5:$J$67<>"OK")*(INSUMOS!$J$5:$J$67<>""),ROW(INSUMOS!$J$5:$J$67)),26),"")),"") | C47: =IFERROR(INDEX(INSUMOS!H:H,IFERROR(SMALL(IF((INSUMOS!$J$5:$J$67<>"OK")*(INSUMOS!$J$5:$J$67<>""),ROW(INSUMOS!$J$5:$J$67)),26),"")),"") | D47: =IFERROR(INDEX(INSUMOS!I:I,IFERROR(SMALL(IF((INSUMOS!$J$5:$J$67<>"OK")*(INSUMOS!$J$5:$J$67<>""),ROW(INSUMOS!$J$5:$J$67)),26),"")),"") | E47: =IFERROR(INDEX(INSUMOS!J:J,IFERROR(SMALL(IF((INSUMOS!$J$5:$J$67<>"OK")*(INSUMOS!$J$5:$J$67<>""),ROW(INSUMOS!$J$5:$J$67)),26),"")),"") | F47: =IFERROR(INDEX(INSUMOS!M:M,IFERROR(SMALL(IF((INSUMOS!$J$5:$J$67<>"OK")*(INSUMOS!$J$5:$J$67<>""),ROW(INSUMOS!$J$5:$J$67)),26),"")),"")
A48: =IFERROR(INDEX(INSUMOS!B:B,IFERROR(SMALL(IF((INSUMOS!$J$5:$J$67<>"OK")*(INSUMOS!$J$5:$J$67<>""),ROW(INSUMOS!$J$5:$J$67)),27),"")),"") | B48: =IFERROR(INDEX(INSUMOS!C:C,IFERROR(SMALL(IF((INSUMOS!$J$5:$J$67<>"OK")*(INSUMOS!$J$5:$J$67<>""),ROW(INSUMOS!$J$5:$J$67)),27),"")),"") | C48: =IFERROR(INDEX(INSUMOS!H:H,IFERROR(SMALL(IF((INSUMOS!$J$5:$J$67<>"OK")*(INSUMOS!$J$5:$J$67<>""),ROW(INSUMOS!$J$5:$J$67)),27),"")),"") | D48: =IFERROR(INDEX(INSUMOS!I:I,IFERROR(SMALL(IF((INSUMOS!$J$5:$J$67<>"OK")*(INSUMOS!$J$5:$J$67<>""),ROW(INSUMOS!$J$5:$J$67)),27),"")),"") | E48: =IFERROR(INDEX(INSUMOS!J:J,IFERROR(SMALL(IF((INSUMOS!$J$5:$J$67<>"OK")*(INSUMOS!$J$5:$J$67<>""),ROW(INSUMOS!$J$5:$J$67)),27),"")),"") | F48: =IFERROR(INDEX(INSUMOS!M:M,IFERROR(SMALL(IF((INSUMOS!$J$5:$J$67<>"OK")*(INSUMOS!$J$5:$J$67<>""),ROW(INSUMOS!$J$5:$J$67)),27),"")),"")
A49: =IFERROR(INDEX(INSUMOS!B:B,IFERROR(SMALL(IF((INSUMOS!$J$5:$J$67<>"OK")*(INSUMOS!$J$5:$J$67<>""),ROW(INSUMOS!$J$5:$J$67)),28),"")),"") | B49: =IFERROR(INDEX(INSUMOS!C:C,IFERROR(SMALL(IF((INSUMOS!$J$5:$J$67<>"OK")*(INSUMOS!$J$5:$J$67<>""),ROW(INSUMOS!$J$5:$J$67)),28),"")),"") | C49: =IFERROR(INDEX(INSUMOS!H:H,IFERROR(SMALL(IF((INSUMOS!$J$5:$J$67<>"OK")*(INSUMOS!$J$5:$J$67<>""),ROW(INSUMOS!$J$5:$J$67)),28),"")),"") | D49: =IFERROR(INDEX(INSUMOS!I:I,IFERROR(SMALL(IF((INSUMOS!$J$5:$J$67<>"OK")*(INSUMOS!$J$5:$J$67<>""),ROW(INSUMOS!$J$5:$J$67)),28),"")),"") | E49: =IFERROR(INDEX(INSUMOS!J:J,IFERROR(SMALL(IF((INSUMOS!$J$5:$J$67<>"OK")*(INSUMOS!$J$5:$J$67<>""),ROW(INSUMOS!$J$5:$J$67)),28),"")),"") | F49: =IFERROR(INDEX(INSUMOS!M:M,IFERROR(SMALL(IF((INSUMOS!$J$5:$J$67<>"OK")*(INSUMOS!$J$5:$J$67<>""),ROW(INSUMOS!$J$5:$J$67)),28),"")),"")
A50: =IFERROR(INDEX(INSUMOS!B:B,IFERROR(SMALL(IF((INSUMOS!$J$5:$J$67<>"OK")*(INSUMOS!$J$5:$J$67<>""),ROW(INSUMOS!$J$5:$J$67)),29),"")),"") | B50: =IFERROR(INDEX(INSUMOS!C:C,IFERROR(SMALL(IF((INSUMOS!$J$5:$J$67<>"OK")*(INSUMOS!$J$5:$J$67<>""),ROW(INSUMOS!$J$5:$J$67)),29),"")),"") | C50: =IFERROR(INDEX(INSUMOS!H:H,IFERROR(SMALL(IF((INSUMOS!$J$5:$J$67<>"OK")*(INSUMOS!$J$5:$J$67<>""),ROW(INSUMOS!$J$5:$J$67)),29),"")),"") | D50: =IFERROR(INDEX(INSUMOS!I:I,IFERROR(SMALL(IF((INSUMOS!$J$5:$J$67<>"OK")*(INSUMOS!$J$5:$J$67<>""),ROW(INSUMOS!$J$5:$J$67)),29),"")),"") | E50: =IFERROR(INDEX(INSUMOS!J:J,IFERROR(SMALL(IF((INSUMOS!$J$5:$J$67<>"OK")*(INSUMOS!$J$5:$J$67<>""),ROW(INSUMOS!$J$5:$J$67)),29),"")),"") | F50: =IFERROR(INDEX(INSUMOS!M:M,IFERROR(SMALL(IF((INSUMOS!$J$5:$J$67<>"OK")*(INSUMOS!$J$5:$J$67<>""),ROW(INSUMOS!$J$5:$J$67)),29),"")),"")
A51: =IFERROR(INDEX(INSUMOS!B:B,IFERROR(SMALL(IF((INSUMOS!$J$5:$J$67<>"OK")*(INSUMOS!$J$5:$J$67<>""),ROW(INSUMOS!$J$5:$J$67)),30),"")),"") | B51: =IFERROR(INDEX(INSUMOS!C:C,IFERROR(SMALL(IF((INSUMOS!$J$5:$J$67<>"OK")*(INSUMOS!$J$5:$J$67<>""),ROW(INSUMOS!$J$5:$J$67)),30),"")),"") | C51: =IFERROR(INDEX(INSUMOS!H:H,IFERROR(SMALL(IF((INSUMOS!$J$5:$J$67<>"OK")*(INSUMOS!$J$5:$J$67<>""),ROW(INSUMOS!$J$5:$J$67)),30),"")),"") | D51: =IFERROR(INDEX(INSUMOS!I:I,IFERROR(SMALL(IF((INSUMOS!$J$5:$J$67<>"OK")*(INSUMOS!$J$5:$J$67<>""),ROW(INSUMOS!$J$5:$J$67)),30),"")),"") | E51: =IFERROR(INDEX(INSUMOS!J:J,IFERROR(SMALL(IF((INSUMOS!$J$5:$J$67<>"OK")*(INSUMOS!$J$5:$J$67<>""),ROW(INSUMOS!$J$5:$J$67)),30),"")),"") | F51: =IFERROR(INDEX(INSUMOS!M:M,IFERROR(SMALL(IF((INSUMOS!$J$5:$J$67<>"OK")*(INSUMOS!$J$5:$J$67<>""),ROW(INSUMOS!$J$5:$J$67)),30),"")),"")

Sheet INSUMOS
A1: 📦 INSUMOS - Control de Stock
A2: 🟡 Amarillo = tú lo llenas | ⚪ Gris = se calcula solo | Llená stock inicial y Costo base (col. N). El Costo unitario sube solo cuando comprás más caro; si baja, se mantiene.
A4: Código | B4: Nombre | C4: Categoría | D4: Unidad | E4: Stock inicial | F4: Total comprado | G4: Total consumido | H4: Stock actual | I4: Stock mínimo | J4: Estado | K4: Costo unitario | L4: Valor en stock | M4: Notas | N4: Costo base
A5: I001 | B5: Papel bond A6 105 gr | C5: Papel | D5: hoja | E5: 0 | F5: =IFERROR(SUMIFS(COMPRAS!C:C,COMPRAS!B:B,B5),0) | G5: =IFERROR(SUMIFS(RECETAS!E:E,RECETAS!B:B,B5),0) | H5: =E5+F5-G5-IFERROR(SUMIFS(PERDIDAS!C:C,PERDIDAS!B:B,B5),0) | I5: 0 | J5: =IF(H5<=0,"SIN STOCK",IF(H5<=I5,"BAJO STOCK","OK")) | K5: =MAX(N5+0,IFERROR(_xlfn.MAXIFS(COMPRAS!$F$5:$F$504,COMPRAS!$B$5:$B$504,B5),0)) | L5: =IFERROR(H5*K5,0) | M5: Se compra por resma. Ingresá el stock en hojas.
A6: I002 | B6: Papel bond A5 90 gr | C6: Papel | D6: hoja | E6: 0 | F6: =IFERROR(SUMIFS(COMPRAS!C:C,COMPRAS!B:B,B6),0) | G6: =IFERROR(SUMIFS(RECETAS!E:E,RECETAS!B:B,B6),0) | H6: =E6+F6-G6-IFERROR(SUMIFS(PERDIDAS!C:C,PERDIDAS!B:B,B6),0) | I6: 0 | J6: =IF(H6<=0,"SIN STOCK",IF(H6<=I6,"BAJO STOCK","OK")) | K6: =MAX(N6+0,IFERROR(_xlfn.MAXIFS(COMPRAS!$F$5:$F$504,COMPRAS!$B$5:$B$504,B6),0)) | L6: =IFERROR(H6*K6,0) | M6: Se compra por resma. Ingresá el stock en hojas.
A7: I003 | B7: Papel bond A5 105 gr | C7: Papel | D7: hoja | E7: 0 | F7: =IFERROR(SUMIFS(COMPRAS!C:C,COMPRAS!B:B,B7),0) | G7: =IFERROR(SUMIFS(RECETAS!E:E,RECETAS!B:B,B7),0) | H7: =E7+F7-G7-IFERROR(SUMIFS(PERDIDAS!C:C,PERDIDAS!B:B,B7),0) | I7: 0 | J7: =IF(H7<=0,"SIN STOCK",IF(H7<=I7,"BAJO STOCK","OK")) | K7: =MAX(N7+0,IFERROR(_xlfn.MAXIFS(COMPRAS!$F$5:$F$504,COMPRAS!$B$5:$B$504,B7),0)) | L7: =IFERROR(H7*K7,0) | M7: Se compra por resma. Ingresá el stock en hojas.
A8: I004 | B8: Papel bond B5 105 gr | C8: Papel | D8: hoja | E8: 0 | F8: =IFERROR(SUMIFS(COMPRAS!C:C,COMPRAS!B:B,B8),0) | G8: =IFERROR(SUMIFS(RECETAS!E:E,RECETAS!B:B,B8),0) | H8: =E8+F8-G8-IFERROR(SUMIFS(PERDIDAS!C:C,PERDIDAS!B:B,B8),0) | I8: 0 | J8: =IF(H8<=0,"SIN STOCK",IF(H8<=I8,"BAJO STOCK","OK")) | K8: =MAX(N8+0,IFERROR(_xlfn.MAXIFS(COMPRAS!$F$5:$F$504,COMPRAS!$B$5:$B$504,B8),0)) | L8: =IFERROR(H8*K8,0) | M8: Se compra por resma. Ingresá el stock en hojas.
A9: I005 | B9: Papel bond A4 105 gr | C9: Papel | D9: hoja | E9: 0 | F9: =IFERROR(SUMIFS(COMPRAS!C:C,COMPRAS!B:B,B9),0) | G9: =IFERROR(SUMIFS(RECETAS!E:E,RECETAS!B:B,B9),0) | H9: =E9+F9-G9-IFERROR(SUMIFS(PERDIDAS!C:C,PERDIDAS!B:B,B9),0) | I9: 0 | J9: =IF(H9<=0,"SIN STOCK",IF(H9<=I9,"BAJO STOCK","OK")) | K9: =MAX(N9+0,IFERROR(_xlfn.MAXIFS(COMPRAS!$F$5:$F$504,COMPRAS!$B$5:$B$504,B9),0)) | L9: =IFERROR(H9*K9,0) | M9: Se compra por resma. Ingresá el stock en hojas.
A10: I006 | B10: Papel bond Carta 105 gr | C10: Papel | D10: hoja | E10: 0 | F10: =IFERROR(SUMIFS(COMPRAS!C:C,COMPRAS!B:B,B10),0) | G10: =IFERROR(SUMIFS(RECETAS!E:E,RECETAS!B:B,B10),0) | H10: =E10+F10-G10-IFERROR(SUMIFS(PERDIDAS!C:C,PERDIDAS!B:B,B10),0) | I10: 0 | J10: =IF(H10<=0,"SIN STOCK",IF(H10<=I10,"BAJO STOCK","OK")) | K10: =MAX(N10+0,IFERROR(_xlfn.MAXIFS(COMPRAS!$F$5:$F$504,COMPRAS!$B$5:$B$504,B10),0)) | L10: =IFERROR(H10*K10,0) | M10: Se compra por resma. Ingresá el stock en hojas.
A11: I007 | B11: Papel foto adhesivo brillo | C11: Papel | D11: hoja | E11: 0 | F11: =IFERROR(SUMIFS(COMPRAS!C:C,COMPRAS!B:B,B11),0) | G11: =IFERROR(SUMIFS(RECETAS!E:E,RECETAS!B:B,B11),0) | H11: =E11+F11-G11-IFERROR(SUMIFS(PERDIDAS!C:C,PERDIDAS!B:B,B11),0) | I11: 0 | J11: =IF(H11<=0,"SIN STOCK",IF(H11<=I11,"BAJO STOCK","OK")) | K11: =MAX(N11+0,IFERROR(_xlfn.MAXIFS(COMPRAS!$F$5:$F$504,COMPRAS!$B$5:$B$504,B11),0)) | L11: =IFERROR(H11*K11,0) | M11: Compra resma 50 / uso por hoja.
A12: I008 | B12: Papel foto adhesivo matte | C12: Papel | D12: hoja | E12: 0 | F12: =IFERROR(SUMIFS(COMPRAS!C:C,COMPRAS!B:B,B12),0) | G12: =IFERROR(SUMIFS(RECETAS!E:E,RECETAS!B:B,B12),0) | H12: =E12+F12-G12-IFERROR(SUMIFS(PERDIDAS!C:C,PERDIDAS!B:B,B12),0) | I12: 0 | J12: =IF(H12<=0,"SIN STOCK",IF(H12<=I12,"BAJO STOCK","OK")) | K12: =MAX(N12+0,IFERROR(_xlfn.MAXIFS(COMPRAS!$F$5:$F$504,COMPRAS!$B$5:$B$504,B12),0)) | L12: =IFERROR(H12*K12,0) | M12: Compra resma 50 / uso por hoja.
A13: I009 | B13: Papel foto A4 | C13: Papel | D13: hoja | E13: 0 | F13: =IFERROR(SUMIFS(COMPRAS!C:C,COMPRAS!B:B,B13),0) | G13: =IFERROR(SUMIFS(RECETAS!E:E,RECETAS!B:B,B13),0) | H13: =E13+F13-G13-IFERROR(SUMIFS(PERDIDAS!C:C,PERDIDAS!B:B,B13),0) | I13: 0 | J13: =IF(H13<=0,"SIN STOCK",IF(H13<=I13,"BAJO STOCK","OK")) | K13: =MAX(N13+0,IFERROR(_xlfn.MAXIFS(COMPRAS!$F$5:$F$504,COMPRAS!$B$5:$B$504,B13),0)) | L13: =IFERROR(H13*K13,0) | M13: Compra resma 50 / uso por hoja.
A14: I010 | B14: Papel adhesivo Lee | C14: Papel | D14: hoja | E14: 0 | F14: =IFERROR(SUMIFS(COMPRAS!C:C,COMPRAS!B:B,B14),0) | G14: =IFERROR(SUMIFS(RECETAS!E:E,RECETAS!B:B,B14),0) | H14: =E14+F14-G14-IFERROR(SUMIFS(PERDIDAS!C:C,PERDIDAS!B:B,B14),0) | I14: 0 | J14: =IF(H14<=0,"SIN STOCK",IF(H14<=I14,"BAJO STOCK","OK")) | K14: =MAX(N14+0,IFERROR(_xlfn.MAXIFS(COMPRAS!$F$5:$F$504,COMPRAS!$B$5:$B$504,B14),0)) | L14: =IFERROR(H14*K14,0) | M14: Compra resma 50 / uso por hoja.
A15: I011 | B15: Papel vinilo waterproof | C15: Papel | D15: hoja | E15: 0 | F15: =IFERROR(SUMIFS(COMPRAS!C:C,COMPRAS!B:B,B15),0) | G15: =IFERROR(SUMIFS(RECETAS!E:E,RECETAS!B:B,B15),0) | H15: =E15+F15-G15-IFERROR(SUMIFS(PERDIDAS!C:C,PERDIDAS!B:B,B15),0) | I15: 0 | J15: =IF(H15<=0,"SIN STOCK",IF(H15<=I15,"BAJO STOCK","OK")) | K15: =MAX(N15+0,IFERROR(_xlfn.MAXIFS(COMPRAS!$F$5:$F$504,COMPRAS!$B$5:$B$504,B15),0)) | L15: =IFERROR(H15*K15,0) | M15: Compra resma 50 / uso por hoja.
A16: I012 | B16: Papel vinilo tornasol | C16: Papel | D16: hoja | E16: 0 | F16: =IFERROR(SUMIFS(COMPRAS!C:C,COMPRAS!B:B,B16),0) | G16: =IFERROR(SUMIFS(RECETAS!E:E,RECETAS!B:B,B16),0) | H16: =E16+F16-G16-IFERROR(SUMIFS(PERDIDAS!C:C,PERDIDAS!B:B,B16),0) | I16: 0 | J16: =IF(H16<=0,"SIN STOCK",IF(H16<=I16,"BAJO STOCK","OK")) | K16: =MAX(N16+0,IFERROR(_xlfn.MAXIFS(COMPRAS!$F$5:$F$504,COMPRAS!$B$5:$B$504,B16),0)) | L16: =IFERROR(H16*K16,0) | M16: Compra resma 50 / uso por hoja.
... A22: I018 | B22: Papel couché | C22: Papel | D22: hoja | E22: 0 | F22: =IFERROR(SUMIFS(COMPRAS!C:C,COMPRAS!B:B,B22),0) | G22: =IFERROR(SUMIFS(RECETAS!E:E,RECETAS!B:B,B22),0) | H22: =E22+F22-G22-IFERROR(SUMIFS(PERDIDAS!C:C,PERDIDAS!B:B,B22),0) | I22: 0 | J22: =IF(H22<=0,"SIN STOCK",IF(H22<=I22,"BAJO STOCK","OK")) | K22: =MAX(N22+0,IFERROR(_xlfn.MAXIFS(COMPRAS!$F$5:$F$504,COMPRAS!$B$5:$B$504,B22),0)) | L22: =IFERROR(H22*K22,0) | M22: Compra resma 50 / uso por hoja.
A23: I019 | B23: Hojas carta 75 gr | C23: Papel | D23: hoja | E23: 0 | F23: =IFERROR(SUMIFS(COMPRAS!C:C,COMPRAS!B:B,B23),0) | G23: =IFERROR(SUMIFS(RECETAS!E:E,RECETAS!B:B,B23),0) | H23: =E23+F23-G23-IFERROR(SUMIFS(PERDIDAS!C:C,PERDIDAS!B:B,B23),0) | I23: 0 | J23: =IF(H23<=0,"SIN STOCK",IF(H23<=I23,"BAJO STOCK","OK")) | K23: =MAX(N23+0,IFERROR(_xlfn.MAXIFS(COMPRAS!$F$5:$F$504,COMPRAS!$B$5:$B$504,B23),0)) | L23: =IFERROR(H23*K23,0)
A24: I020 | B24: Autocopiativo | C24: Papel | D24: hoja | E24: 0 | F24: =IFERROR(SUMIFS(COMPRAS!C:C,COMPRAS!B:B,B24),0) | G24: =IFERROR(SUMIFS(RECETAS!E:E,RECETAS!B:B,B24),0) | H24: =E24+F24-G24-IFERROR(SUMIFS(PERDIDAS!C:C,PERDIDAS!B:B,B24),0) | I24: 0 | J24: =IF(H24<=0,"SIN STOCK",IF(H24<=I24,"BAJO STOCK","OK")) | K24: =MAX(N24+0,IFERROR(_xlfn.MAXIFS(COMPRAS!$F$5:$F$504,COMPRAS!$B$5:$B$504,B24),0)) | L24: =IFERROR(H24*K24,0)
A25: I021 | B25: Cartón piedra A6 | C25: Cartón | D25: unidad | E25: 0 | F25: =IFERROR(SUMIFS(COMPRAS!C:C,COMPRAS!B:B,B25),0) | G25: =IFERROR(SUMIFS(RECETAS!E:E,RECETAS!B:B,B25),0) | H25: =E25+F25-G25-IFERROR(SUMIFS(PERDIDAS!C:C,PERDIDAS!B:B,B25),0) | I25: 0 | J25: =IF(H25<=0,"SIN STOCK",IF(H25<=I25,"BAJO STOCK","OK")) | K25: =MAX(N25+0,IFERROR(_xlfn.MAXIFS(COMPRAS!$F$5:$F$504,COMPRAS!$B$5:$B$504,B25),0)) | L25: =IFERROR(H25*K25,0)
A26: I022 | B26: Cartón piedra A5 | C26: Cartón | D26: unidad | E26: 0 | F26: =IFERROR(SUMIFS(COMPRAS!C:C,COMPRAS!B:B,B26),0) | G26: =IFERROR(SUMIFS(RECETAS!E:E,RECETAS!B:B,B26),0) | H26: =E26+F26-G26-IFERROR(SUMIFS(PERDIDAS!C:C,PERDIDAS!B:B,B26),0) | I26: 0 | J26: =IF(H26<=0,"SIN STOCK",IF(H26<=I26,"BAJO STOCK","OK")) | K26: =MAX(N26+0,IFERROR(_xlfn.MAXIFS(COMPRAS!$F$5:$F$504,COMPRAS!$B$5:$B$504,B26),0)) | L26: =IFERROR(H26*K26,0)
A27: I023 | B27: Cartón piedra B5 | C27: Cartón | D27: unidad | E27: 0 | F27: =IFERROR(SUMIFS(COMPRAS!C:C,COMPRAS!B:B,B27),0) | G27: =IFERROR(SUMIFS(RECETAS!E:E,RECETAS!B:B,B27),0) | H27: =E27+F27-G27-IFERROR(SUMIFS(PERDIDAS!C:C,PERDIDAS!B:B,B27),0) | I27: 0 | J27: =IF(H27<=0,"SIN STOCK",IF(H27<=I27,"BAJO STOCK","OK")) | K27: =MAX(N27+0,IFERROR(_xlfn.MAXIFS(COMPRAS!$F$5:$F$504,COMPRAS!$B$5:$B$504,B27),0)) | L27: =IFERROR(H27*K27,0)
A28: I024 | B28: Cartón piedra A4 | C28: Cartón | D28: unidad | E28: 0 | F28: =IFERROR(SUMIFS(COMPRAS!C:C,COMPRAS!B:B,B28),0) | G28: =IFERROR(SUMIFS(RECETAS!E:E,RECETAS!B:B,B28),0) | H28: =E28+F28-G28-IFERROR(SUMIFS(PERDIDAS!C:C,PERDIDAS!B:B,B28),0) | I28: 0 | J28: =IF(H28<=0,"SIN STOCK",IF(H28<=I28,"BAJO STOCK","OK")) | K28: =MAX(N28+0,IFERROR(_xlfn.MAXIFS(COMPRAS!$F$5:$F$504,COMPRAS!$B$5:$B$504,B28),0)) | L28: =IFERROR(H28*K28,0)
A29: I025 | B29: Laminado en frío A4 brillo | C29: Laminado | D29: hoja A4 | E29: 0 | F29: =IFERROR(SUMIFS(COMPRAS!C:C,COMPRAS!B:B,B29),0) | G29: =IFERROR(SUMIFS(RECETAS!E:E,RECETAS!B:B,B29),0) | H29: =E29+F29-G29-IFERROR(SUMIFS(PERDIDAS!C:C,PERDIDAS!B:B,B29),0) | I29: 0 | J29: =IF(H29<=0,"SIN STOCK",IF(H29<=I29,"BAJO STOCK","OK")) | K29: =MAX(N29+0,IFERROR(_xlfn.MAXIFS(COMPRAS!$F$5:$F$504,COMPRAS!$B$5:$B$504,B29),0)) | L29: =IFERROR(H29*K29,0) | M29: Compra en rollo. Convertí el rollo a hojas A4 equivalentes.
A30: I026 | B30: Laminado en frío A4 matte | C30: Laminado | D30: hoja A4 | E30: 0 | F30: =IFERROR(SUMIFS(COMPRAS!C:C,COMPRAS!B:B,B30),0) | G30: =IFERROR(SUMIFS(RECETAS!E:E,RECETAS!B:B,B30),0) | H30: =E30+F30-G30-IFERROR(SUMIFS(PERDIDAS!C:C,PERDIDAS!B:B,B30),0) | I30: 0 | J30: =IF(H30<=0,"SIN STOCK",IF(H30<=I30,"BAJO STOCK","OK")) | K30: =MAX(N30+0,IFERROR(_xlfn.MAXIFS(COMPRAS!$F$5:$F$504,COMPRAS!$B$5:$B$504,B30),0)) | L30: =IFERROR(H30*K30,0) | M30: Compra en rollo. Convertí el rollo a hojas A4 equivalentes.
A31: I027 | B31: Mica termolaminado A4 | C31: Laminado | D31: unidad | E31: 0 | F31: =IFERROR(SUMIFS(COMPRAS!C:C,COMPRAS!B:B,B31),0) | G31: =IFERROR(SUMIFS(RECETAS!E:E,RECETAS!B:B,B31),0) | H31: =E31+F31-G31-IFERROR(SUMIFS(PERDIDAS!C:C,PERDIDAS!B:B,B31),0) | I31: 0 | J31: =IF(H31<=0,"SIN STOCK",IF(H31<=I31,"BAJO STOCK","OK")) | K31: =MAX(N31+0,IFERROR(_xlfn.MAXIFS(COMPRAS!$F$5:$F$504,COMPRAS!$B$5:$B$504,B31),0)) | L31: =IFERROR(H31*K31,0) | M31: Compra resma 50 / uso por unidad.
A32: I028 | B32: Mica termolaminado Carta | C32: Laminado | D32: unidad | E32: 0 | F32: =IFERROR(SUMIFS(COMPRAS!C:C,COMPRAS!B:B,B32),0) | G32: =IFERROR(SUMIFS(RECETAS!E:E,RECETAS!B:B,B32),0) | H32: =E32+F32-G32-IFERROR(SUMIFS(PERDIDAS!C:C,PERDIDAS!B:B,B32),0) | I32: 0 | J32: =IF(H32<=0,"SIN STOCK",IF(H32<=I32,"BAJO STOCK","OK")) | K32: =MAX(N32+0,IFERROR(_xlfn.MAXIFS(COMPRAS!$F$5:$F$504,COMPRAS!$B$5:$B$504,B32),0)) | L32: =IFERROR(H32*K32,0) | M32: Compra resma 50 / uso por unidad.
A33: I029 | B33: Espirales | C33: Encuadernación | D33: unidad | E33: 0 | F33: =IFERROR(SUMIFS(COMPRAS!C:C,COMPRAS!B:B,B33),0) | G33: =IFERROR(SUMIFS(RECETAS!E:E,RECETAS!B:B,B33),0) | H33: =E33+F33-G33-IFERROR(SUMIFS(PERDIDAS!C:C,PERDIDAS!B:B,B33),0) | I33: 0 | J33: =IF(H33<=0,"SIN STOCK",IF(H33<=I33,"BAJO STOCK","OK")) | K33: =MAX(N33+0,IFERROR(_xlfn.MAXIFS(COMPRAS!$F$5:$F$504,COMPRAS!$B$5:$B$504,B33),0)) | L33: =IFERROR(H33*K33,0)
A34: I030 | B34: Discos 24 mm | C34: Encuadernación | D34: unidad | E34: 0 | F34: =IFERROR(SUMIFS(COMPRAS!C:C,COMPRAS!B:B,B34),0) | G34: =IFERROR(SUMIFS(RECETAS!E:E,RECETAS!B:B,B34),0) | H34: =E34+F34-G34-IFERROR(SUMIFS(PERDIDAS!C:C,PERDIDAS!B:B,B34),0) | I34: 0 | J34: =IF(H34<=0,"SIN STOCK",IF(H34<=I34,"BAJO STOCK","OK")) | K34: =MAX(N34+0,IFERROR(_xlfn.MAXIFS(COMPRAS!$F$5:$F$504,COMPRAS!$B$5:$B$504,B34),0)) | L34: =IFERROR(H34*K34,0) | M34: AliExpress.
A35: I031 | B35: Discos 28 mm | C35: Encuadernación | D35: unidad | E35: 0 | F35: =IFERROR(SUMIFS(COMPRAS!C:C,COMPRAS!B:B,B35),0) | G35: =IFERROR(SUMIFS(RECETAS!E:E,RECETAS!B:B,B35),0) | H35: =E35+F35-G35-IFERROR(SUMIFS(PERDIDAS!C:C,PERDIDAS!B:B,B35),0) | I35: 0 | J35: =IF(H35<=0,"SIN STOCK",IF(H35<=I35,"BAJO STOCK","OK")) | K35: =MAX(N35+0,IFERROR(_xlfn.MAXIFS(COMPRAS!$F$5:$F$504,COMPRAS!$B$5:$B$504,B35),0)) | L35: =IFERROR(H35*K35,0) | M35: AliExpress.
A36: I032 | B36: Discos 33 mm | C36: Encuadernación | D36: unidad | E36: 0 | F36: =IFERROR(SUMIFS(COMPRAS!C:C,COMPRAS!B:B,B36),0) | G36: =IFERROR(SUMIFS(RECETAS!E:E,RECETAS!B:B,B36),0) | H36: =E36+F36-G36-IFERROR(SUMIFS(PERDIDAS!C:C,PERDIDAS!B:B,B36),0) | I36: 0 | J36: =IF(H36<=0,"SIN STOCK",IF(H36<=I36,"BAJO STOCK","OK")) | K36: =MAX(N36+0,IFERROR(_xlfn.MAXIFS(COMPRAS!$F$5:$F$504,COMPRAS!$B$5:$B$504,B36),0)) | L36: =IFERROR(H36*K36,0) | M36: AliExpress.
A37: I033 | B37: Anillos 16 mm (5/8") | C37: Encuadernación | D37: unidad | E37: 0 | F37: =IFERROR(SUMIFS(COMPRAS!C:C,COMPRAS!B:B,B37),0) | G37: =IFERROR(SUMIFS(RECETAS!E:E,RECETAS!B:B,B37),0) | H37: =E37+F37-G37-IFERROR(SUMIFS(PERDIDAS!C:C,PERDIDAS!B:B,B37),0) | I37: 0 | J37: =IF(H37<=0,"SIN STOCK",IF(H37<=I37,"BAJO STOCK","OK")) | K37: =MAX(N37+0,IFERROR(_xlfn.MAXIFS(COMPRAS!$F$5:$F$504,COMPRAS!$B$5:$B$504,B37),0)) | L37: =IFERROR(H37*K37,0) | M37: Cada anillo = 1 unidad.
A38: I034 | B38: Anillos 19 mm (3/4") | C38: Encuadernación | D38: unidad | E38: 0 | F38: =IFERROR(SUMIFS(COMPRAS!C:C,COMPRAS!B:B,B38),0) | G38: =IFERROR(SUMIFS(RECETAS!E:E,RECETAS!B:B,B38),0) | H38: =E38+F38-G38-IFERROR(SUMIFS(PERDIDAS!C:C,PERDIDAS!B:B,B38),0) | I38: 0 | J38: =IF(H38<=0,"SIN STOCK",IF(H38<=I38,"BAJO STOCK","OK")) | K38: =MAX(N38+0,IFERROR(_xlfn.MAXIFS(COMPRAS!$F$5:$F$504,COMPRAS!$B$5:$B$504,B38),0)) | L38: =IFERROR(H38*K38,0) | M38: Cada anillo = 1 unidad.
A39: I035 | B39: Anillos 22 mm (7/8") | C39: Encuadernación | D39: unidad | E39: 0 | F39: =IFERROR(SUMIFS(COMPRAS!C:C,COMPRAS!B:B,B39),0) | G39: =IFERROR(SUMIFS(RECETAS!E:E,RECETAS!B:B,B39),0) | H39: =E39+F39-G39-IFERROR(SUMIFS(PERDIDAS!C:C,PERDIDAS!B:B,B39),0) | I39: 0 | J39: =IF(H39<=0,"SIN STOCK",IF(H39<=I39,"BAJO STOCK","OK")) | K39: =MAX(N39+0,IFERROR(_xlfn.MAXIFS(COMPRAS!$F$5:$F$504,COMPRAS!$B$5:$B$504,B39),0)) | L39: =IFERROR(H39*K39,0) | M39: Cada anillo = 1 unidad.
A40: I036 | B40: Corchete | C40: Encuadernación | D40: unidad | E40: 0 | F40: =IFERROR(SUMIFS(COMPRAS!C:C,COMPRAS!B:B,B40),0) | G40: =IFERROR(SUMIFS(RECETAS!E:E,RECETAS!B:B,B40),0) | H40: =E40+F40-G40-IFERROR(SUMIFS(PERDIDAS!C:C,PERDIDAS!B:B,B40),0) | I40: 0 | J40: =IF(H40<=0,"SIN STOCK",IF(H40<=I40,"BAJO STOCK","OK")) | K40: =MAX(N40+0,IFERROR(_xlfn.MAXIFS(COMPRAS!$F$5:$F$504,COMPRAS!$B$5:$B$504,B40),0)) | L40: =IFERROR(H40*K40,0) | M40: Completar costo.
A41: I037 | B41: Anillas de metal | C41: Encuadernación | D41: unidad | E41: 0 | F41: =IFERROR(SUMIFS(COMPRAS!C:C,COMPRAS!B:B,B41),0) | G41: =IFERROR(SUMIFS(RECETAS!E:E,RECETAS!B:B,B41),0) | H41: =E41+F41-G41-IFERROR(SUMIFS(PERDIDAS!C:C,PERDIDAS!B:B,B41),0) | I41: 0 | J41: =IF(H41<=0,"SIN STOCK",IF(H41<=I41,"BAJO STOCK","OK")) | K41: =MAX(N41+0,IFERROR(_xlfn.MAXIFS(COMPRAS!$F$5:$F$504,COMPRAS!$B$5:$B$504,B41),0)) | L41: =IFERROR(H41*K41,0)
A42: I038 | B42: Bolsa celofán stickers | C42: Bolsas | D42: unidad | E42: 0 | F42: =IFERROR(SUMIFS(COMPRAS!C:C,COMPRAS!B:B,B42),0) | G42: =IFERROR(SUMIFS(RECETAS!E:E,RECETAS!B:B,B42),0) | H42: =E42+F42-G42-IFERROR(SUMIFS(PERDIDAS!C:C,PERDIDAS!B:B,B42),0) | I42: 0 | J42: =IF(H42<=0,"SIN STOCK",IF(H42<=I42,"BAJO STOCK","OK")) | K42: =MAX(N42+0,IFERROR(_xlfn.MAXIFS(COMPRAS!$F$5:$F$504,COMPRAS!$B$5:$B$504,B42),0)) | L42: =IFERROR(H42*K42,0)
A43: I039 | B43: Bolsa celofán marcapáginas | C43: Bolsas | D43: unidad | E43: 0 | F43: =IFERROR(SUMIFS(COMPRAS!C:C,COMPRAS!B:B,B43),0) | G43: =IFERROR(SUMIFS(RECETAS!E:E,RECETAS!B:B,B43),0) | H43: =E43+F43-G43-IFERROR(SUMIFS(PERDIDAS!C:C,PERDIDAS!B:B,B43),0) | I43: 0 | J43: =IF(H43<=0,"SIN STOCK",IF(H43<=I43,"BAJO STOCK","OK")) | K43: =MAX(N43+0,IFERROR(_xlfn.MAXIFS(COMPRAS!$F$5:$F$504,COMPRAS!$B$5:$B$504,B43),0)) | L43: =IFERROR(H43*K43,0)
A44: I040 | B44: Bolsa celofán 20x30 | C44: Bolsas | D44: unidad | E44: 0 | F44: =IFERROR(SUMIFS(COMPRAS!C:C,COMPRAS!B:B,B44),0) | G44: =IFERROR(SUMIFS(RECETAS!E:E,RECETAS!B:B,B44),0) | H44: =E44+F44-G44-IFERROR(SUMIFS(PERDIDAS!C:C,PERDIDAS!B:B,B44),0) | I44: 0 | J44: =IF(H44<=0,"SIN STOCK",IF(H44<=I44,"BAJO STOCK","OK")) | K44: =MAX(N44+0,IFERROR(_xlfn.MAXIFS(COMPRAS!$F$5:$F$504,COMPRAS!$B$5:$B$504,B44),0)) | L44: =IFERROR(H44*K44,0)
A45: I041 | B45: Bolsa de papel 14x20x8 | C45: Bolsas | D45: unidad | E45: 0 | F45: =IFERROR(SUMIFS(COMPRAS!C:C,COMPRAS!B:B,B45),0) | G45: =IFERROR(SUMIFS(RECETAS!E:E,RECETAS!B:B,B45),0) | H45: =E45+F45-G45-IFERROR(SUMIFS(PERDIDAS!C:C,PERDIDAS!B:B,B45),0) | I45: 0 | J45: =IF(H45<=0,"SIN STOCK",IF(H45<=I45,"BAJO STOCK","OK")) | K45: =MAX(N45+0,IFERROR(_xlfn.MAXIFS(COMPRAS!$F$5:$F$504,COMPRAS!$B$5:$B$504,B45),0)) | L45: =IFERROR(H45*K45,0)
A46: I042 | B46: Imán A4 | C46: Herrajes | D46: hoja A4 | E46: 0 | F46: =IFERROR(SUMIFS(COMPRAS!C:C,COMPRAS!B:B,B46),0) | G46: =IFERROR(SUMIFS(RECETAS!E:E,RECETAS!B:B,B46),0) | H46: =E46+F46-G46-IFERROR(SUMIFS(PERDIDAS!C:C,PERDIDAS!B:B,B46),0) | I46: 0 | J46: =IF(H46<=0,"SIN STOCK",IF(H46<=I46,"BAJO STOCK","OK")) | K46: =MAX(N46+0,IFERROR(_xlfn.MAXIFS(COMPRAS!$F$5:$F$504,COMPRAS!$B$5:$B$504,B46),0)) | L46: =IFERROR(H46*K46,0) | M46: Compra en rollo. Convertí a hojas A4 equivalentes.
A47: I043 | B47: Velcro adhesivo | C47: Herrajes | D47: unidad | E47: 0 | F47: =IFERROR(SUMIFS(COMPRAS!C:C,COMPRAS!B:B,B47),0) | G47: =IFERROR(SUMIFS(RECETAS!E:E,RECETAS!B:B,B47),0) | H47: =E47+F47-G47-IFERROR(SUMIFS(PERDIDAS!C:C,PERDIDAS!B:B,B47),0) | I47: 0 | J47: =IF(H47<=0,"SIN STOCK",IF(H47<=I47,"BAJO STOCK","OK")) | K47: =MAX(N47+0,IFERROR(_xlfn.MAXIFS(COMPRAS!$F$5:$F$504,COMPRAS!$B$5:$B$504,B47),0)) | L47: =IFERROR(H47*K47,0)
A48: I044 | B48: Perno broche bolita | C48: Herrajes | D48: unidad | E48: 0 | F48: =IFERROR(SUMIFS(COMPRAS!C:C,COMPRAS!B:B,B48),0) | G48: =IFERROR(SUMIFS(RECETAS!E:E,RECETAS!B:B,B48),0) | H48: =E48+F48-G48-IFERROR(SUMIFS(PERDIDAS!C:C,PERDIDAS!B:B,B48),0) | I48: 0 | J48: =IF(H48<=0,"SIN STOCK",IF(H48<=I48,"BAJO STOCK","OK")) | K48: =MAX(N48+0,IFERROR(_xlfn.MAXIFS(COMPRAS!$F$5:$F$504,COMPRAS!$B$5:$B$504,B48),0)) | L48: =IFERROR(H48*K48,0)
A49: I045 | B49: Perno chicago | C49: Herrajes | D49: unidad | E49: 0 | F49: =IFERROR(SUMIFS(COMPRAS!C:C,COMPRAS!B:B,B49),0) | G49: =IFERROR(SUMIFS(RECETAS!E:E,RECETAS!B:B,B49),0) | H49: =E49+F49-G49-IFERROR(SUMIFS(PERDIDAS!C:C,PERDIDAS!B:B,B49),0) | I49: 0 | J49: =IF(H49<=0,"SIN STOCK",IF(H49<=I49,"BAJO STOCK","OK")) | K49: =MAX(N49+0,IFERROR(_xlfn.MAXIFS(COMPRAS!$F$5:$F$504,COMPRAS!$B$5:$B$504,B49),0)) | L49: =IFERROR(H49*K49,0)
A50: I046 | B50: Broche magnético | C50: Herrajes | D50: unidad | E50: 0 | F50: =IFERROR(SUMIFS(COMPRAS!C:C,COMPRAS!B:B,B50),0) | G50: =IFERROR(SUMIFS(RECETAS!E:E,RECETAS!B:B,B50),0) | H50: =E50+F50-G50-IFERROR(SUMIFS(PERDIDAS!C:C,PERDIDAS!B:B,B50),0) | I50: 0 | J50: =IF(H50<=0,"SIN STOCK",IF(H50<=I50,"BAJO STOCK","OK")) | K50: =MAX(N50+0,IFERROR(_xlfn.MAXIFS(COMPRAS!$F$5:$F$504,COMPRAS!$B$5:$B$504,B50),0)) | L50: =IFERROR(H50*K50,0)
A51: I047 | B51: Esquineros plateado | C51: Herrajes | D51: unidad | E51: 0 | F51: =IFERROR(SUMIFS(COMPRAS!C:C,COMPRAS!B:B,B51),0) | G51: =IFERROR(SUMIFS(RECETAS!E:E,RECETAS!B:B,B51),0) | H51: =E51+F51-G51-IFERROR(SUMIFS(PERDIDAS!C:C,PERDIDAS!B:B,B51),0) | I51: 0 | J51: =IF(H51<=0,"SIN STOCK",IF(H51<=I51,"BAJO STOCK","OK")) | K51: =MAX(N51+0,IFERROR(_xlfn.MAXIFS(COMPRAS!$F$5:$F$504,COMPRAS!$B$5:$B$504,B51),0)) | L51: =IFERROR(H51*K51,0)
A52: I048 | B52: Esquineros dorados | C52: Herrajes | D52: unidad | E52: 0 | F52: =IFERROR(SUMIFS(COMPRAS!C:C,COMPRAS!B:B,B52),0) | G52: =IFERROR(SUMIFS(RECETAS!E:E,RECETAS!B:B,B52),0) | H52: =E52+F52-G52-IFERROR(SUMIFS(PERDIDAS!C:C,PERDIDAS!B:B,B52),0) | I52: 0 | J52: =IF(H52<=0,"SIN STOCK",IF(H52<=I52,"BAJO STOCK","OK")) | K52: =MAX(N52+0,IFERROR(_xlfn.MAXIFS(COMPRAS!$F$5:$F$504,COMPRAS!$B$5:$B$504,B52),0)) | L52: =IFERROR(H52*K52,0)
A53: I049 | B53: Esquineros cuadriculados | C53: Herrajes | D53: unidad | E53: 0 | F53: =IFERROR(SUMIFS(COMPRAS!C:C,COMPRAS!B:B,B53),0) | G53: =IFERROR(SUMIFS(RECETAS!E:E,RECETAS!B:B,B53),0) | H53: =E53+F53-G53-IFERROR(SUMIFS(PERDIDAS!C:C,PERDIDAS!B:B,B53),0) | I53: 0 | J53: =IF(H53<=0,"SIN STOCK",IF(H53<=I53,"BAJO STOCK","OK")) | K53: =MAX(N53+0,IFERROR(_xlfn.MAXIFS(COMPRAS!$F$5:$F$504,COMPRAS!$B$5:$B$504,B53),0)) | L53: =IFERROR(H53*K53,0)
A54: I050 | B54: Ojetillos | C54: Herrajes | D54: unidad | E54: 0 | F54: =IFERROR(SUMIFS(COMPRAS!C:C,COMPRAS!B:B,B54),0) | G54: =IFERROR(SUMIFS(RECETAS!E:E,RECETAS!B:B,B54),0) | H54: =E54+F54-G54-IFERROR(SUMIFS(PERDIDAS!C:C,PERDIDAS!B:B,B54),0) | I54: 0 | J54: =IF(H54<=0,"SIN STOCK",IF(H54<=I54,"BAJO STOCK","OK")) | K54: =MAX(N54+0,IFERROR(_xlfn.MAXIFS(COMPRAS!$F$5:$F$504,COMPRAS!$B$5:$B$504,B54),0)) | L54: =IFERROR(H54*K54,0)
A55: I051 | B55: Elásticos | C55: Herrajes | D55: unidad | E55: 0 | F55: =IFERROR(SUMIFS(COMPRAS!C:C,COMPRAS!B:B,B55),0) | G55: =IFERROR(SUMIFS(RECETAS!E:E,RECETAS!B:B,B55),0) | H55: =E55+F55-G55-IFERROR(SUMIFS(PERDIDAS!C:C,PERDIDAS!B:B,B55),0) | I55: 0 | J55: =IF(H55<=0,"SIN STOCK",IF(H55<=I55,"BAJO STOCK","OK")) | K55: =MAX(N55+0,IFERROR(_xlfn.MAXIFS(COMPRAS!$F$5:$F$504,COMPRAS!$B$5:$B$504,B55),0)) | L55: =IFERROR(H55*K55,0)
A56: I052 | B56: Clips | C56: Herrajes | D56: unidad | E56: 0 | F56: =IFERROR(SUMIFS(COMPRAS!C:C,COMPRAS!B:B,B56),0) | G56: =IFERROR(SUMIFS(RECETAS!E:E,RECETAS!B:B,B56),0) | H56: =E56+F56-G56-IFERROR(SUMIFS(PERDIDAS!C:C,PERDIDAS!B:B,B56),0) | I56: 0 | J56: =IF(H56<=0,"SIN STOCK",IF(H56<=I56,"BAJO STOCK","OK")) | K56: =MAX(N56+0,IFERROR(_xlfn.MAXIFS(COMPRAS!$F$5:$F$504,COMPRAS!$B$5:$B$504,B56),0)) | L56: =IFERROR(H56*K56,0)
A57: I053 | B57: Tinta impresora 1 - configurar | C57: Impresión | D57: botella | E57: 0 | F57: =IFERROR(SUMIFS(COMPRAS!C:C,COMPRAS!B:B,B57),0) | G57: =IFERROR(SUMIFS(RECETAS!E:E,RECETAS!B:B,B57),0) | H57: =E57+F57-G57-IFERROR(SUMIFS(PERDIDAS!C:C,PERDIDAS!B:B,B57),0) | I57: 0 | J57: =IF(H57<=0,"SIN STOCK",IF(H57<=I57,"BAJO STOCK","OK")) | K57: =MAX(N57+0,IFERROR(_xlfn.MAXIFS(COMPRAS!$F$5:$F$504,COMPRAS!$B$5:$B$504,B57),0)) | L57: =IFERROR(H57*K57,0) | M57: Duplicá esta fila por cada color/impresora. Ej: Negra, Cyan, Magenta, Amarilla.
A58: I054 | B58: Tinta impresora 2 - configurar | C58: Impresión | D58: botella | E58: 0 | F58: =IFERROR(SUMIFS(COMPRAS!C:C,COMPRAS!B:B,B58),0) | G58: =IFERROR(SUMIFS(RECETAS!E:E,RECETAS!B:B,B58),0) | H58: =E58+F58-G58-IFERROR(SUMIFS(PERDIDAS!C:C,PERDIDAS!B:B,B58),0) | I58: 0 | J58: =IF(H58<=0,"SIN STOCK",IF(H58<=I58,"BAJO STOCK","OK")) | K58: =MAX(N58+0,IFERROR(_xlfn.MAXIFS(COMPRAS!$F$5:$F$504,COMPRAS!$B$5:$B$504,B58),0)) | L58: =IFERROR(H58*K58,0) | M58: Duplicá esta fila por cada color/impresora.
A59: I055 | B59: Tinta impresora 3 - configurar | C59: Impresión | D59: botella | E59: 0 | F59: =IFERROR(SUMIFS(COMPRAS!C:C,COMPRAS!B:B,B59),0) | G59: =IFERROR(SUMIFS(RECETAS!E:E,RECETAS!B:B,B59),0) | H59: =E59+F59-G59-IFERROR(SUMIFS(PERDIDAS!C:C,PERDIDAS!B:B,B59),0) | I59: 0 | J59: =IF(H59<=0,"SIN STOCK",IF(H59<=I59,"BAJO STOCK","OK")) | K59: =MAX(N59+0,IFERROR(_xlfn.MAXIFS(COMPRAS!$F$5:$F$504,COMPRAS!$B$5:$B$504,B59),0)) | L59: =IFERROR(H59*K59,0) | M59: Duplicá esta fila por cada color/impresora.
A60: I056 | B60: Traspaso vinilo | C60: Impresión | D60: hoja | E60: 0 | F60: =IFERROR(SUMIFS(COMPRAS!C:C,COMPRAS!B:B,B60),0) | G60: =IFERROR(SUMIFS(RECETAS!E:E,RECETAS!B:B,B60),0) | H60: =E60+F60-G60-IFERROR(SUMIFS(PERDIDAS!C:C,PERDIDAS!B:B,B60),0) | I60: 0 | J60: =IF(H60<=0,"SIN STOCK",IF(H60<=I60,"BAJO STOCK","OK")) | K60: =MAX(N60+0,IFERROR(_xlfn.MAXIFS(COMPRAS!$F$5:$F$504,COMPRAS!$B$5:$B$504,B60),0)) | L60: =IFERROR(H60*K60,0) | M60: Completar costo.
A61: I057 | B61: Vinilo | C61: Impresión | D61: hoja | E61: 0 | F61: =IFERROR(SUMIFS(COMPRAS!C:C,COMPRAS!B:B,B61),0) | G61: =IFERROR(SUMIFS(RECETAS!E:E,RECETAS!B:B,B61),0) | H61: =E61+F61-G61-IFERROR(SUMIFS(PERDIDAS!C:C,PERDIDAS!B:B,B61),0) | I61: 0 | J61: =IF(H61<=0,"SIN STOCK",IF(H61<=I61,"BAJO STOCK","OK")) | K61: =MAX(N61+0,IFERROR(_xlfn.MAXIFS(COMPRAS!$F$5:$F$504,COMPRAS!$B$5:$B$504,B61),0)) | L61: =IFERROR(H61*K61,0) | M61: Completar costo.
A62: I058 | B62: Uso Cameo (lámina de corte) | C62: Impresión | D62: hoja | E62: 0 | F62: =IFERROR(SUMIFS(COMPRAS!C:C,COMPRAS!B:B,B62),0) | G62: =IFERROR(SUMIFS(RECETAS!E:E,RECETAS!B:B,B62),0) | H62: =E62+F62-G62-IFERROR(SUMIFS(PERDIDAS!C:C,PERDIDAS!B:B,B62),0) | I62: 0 | J62: =IF(H62<=0,"SIN STOCK",IF(H62<=I62,"BAJO STOCK","OK")) | K62: =MAX(N62+0,IFERROR(_xlfn.MAXIFS(COMPRAS!$F$5:$F$504,COMPRAS!$B$5:$B$504,B62),0)) | L62: =IFERROR(H62*K62,0)
A63: I059 | B63: Cinta doble faz | C63: Otros | D63: cm | E63: 0 | F63: =IFERROR(SUMIFS(COMPRAS!C:C,COMPRAS!B:B,B63),0) | G63: =IFERROR(SUMIFS(RECETAS!E:E,RECETAS!B:B,B63),0) | H63: =E63+F63-G63-IFERROR(SUMIFS(PERDIDAS!C:C,PERDIDAS!B:B,B63),0) | I63: 0 | J63: =IF(H63<=0,"SIN STOCK",IF(H63<=I63,"BAJO STOCK","OK")) | K63: =MAX(N63+0,IFERROR(_xlfn.MAXIFS(COMPRAS!$F$5:$F$504,COMPRAS!$B$5:$B$504,B63),0)) | L63: =IFERROR(H63*K63,0) | M63: Completar costo por cm.
A64: I060 | B64: Pegamento | C64: Otros | D64: unidad | E64: 0 | F64: =IFERROR(SUMIFS(COMPRAS!C:C,COMPRAS!B:B,B64),0) | G64: =IFERROR(SUMIFS(RECETAS!E:E,RECETAS!B:B,B64),0) | H64: =E64+F64-G64-IFERROR(SUMIFS(PERDIDAS!C:C,PERDIDAS!B:B,B64),0) | I64: 0 | J64: =IF(H64<=0,"SIN STOCK",IF(H64<=I64,"BAJO STOCK","OK")) | K64: =MAX(N64+0,IFERROR(_xlfn.MAXIFS(COMPRAS!$F$5:$F$504,COMPRAS!$B$5:$B$504,B64),0)) | L64: =IFERROR(H64*K64,0)
A65: I061 | B65: Calendario | C65: Otros | D65: unidad | E65: 0 | F65: =IFERROR(SUMIFS(COMPRAS!C:C,COMPRAS!B:B,B65),0) | G65: =IFERROR(SUMIFS(RECETAS!E:E,RECETAS!B:B,B65),0) | H65: =E65+F65-G65-IFERROR(SUMIFS(PERDIDAS!C:C,PERDIDAS!B:B,B65),0) | I65: 0 | J65: =IF(H65<=0,"SIN STOCK",IF(H65<=I65,"BAJO STOCK","OK")) | K65: =MAX(N65+0,IFERROR(_xlfn.MAXIFS(COMPRAS!$F$5:$F$504,COMPRAS!$B$5:$B$504,B65),0)) | L65: =IFERROR(H65*K65,0)
A66: I062 | B66: Calendario bimensual | C66: Otros | D66: unidad | E66: 0 | F66: =IFERROR(SUMIFS(COMPRAS!C:C,COMPRAS!B:B,B66),0) | G66: =IFERROR(SUMIFS(RECETAS!E:E,RECETAS!B:B,B66),0) | H66: =E66+F66-G66-IFERROR(SUMIFS(PERDIDAS!C:C,PERDIDAS!B:B,B66),0) | I66: 0 | J66: =IF(H66<=0,"SIN STOCK",IF(H66<=I66,"BAJO STOCK","OK")) | K66: =MAX(N66+0,IFERROR(_xlfn.MAXIFS(COMPRAS!$F$5:$F$504,COMPRAS!$B$5:$B$504,B66),0)) | L66: =IFERROR(H66*K66,0)
A67: I063 | B67: Calendario 12 meses | C67: Otros | D67: unidad | E67: 0 | F67: =IFERROR(SUMIFS(COMPRAS!C:C,COMPRAS!B:B,B67),0) | G67: =IFERROR(SUMIFS(RECETAS!E:E,RECETAS!B:B,B67),0) | H67: =E67+F67-G67-IFERROR(SUMIFS(PERDIDAS!C:C,PERDIDAS!B:B,B67),0) | I67: 0 | J67: =IF(H67<=0,"SIN STOCK",IF(H67<=I67,"BAJO STOCK","OK")) | K67: =MAX(N67+0,IFERROR(_xlfn.MAXIFS(COMPRAS!$F$5:$F$504,COMPRAS!$B$5:$B$504,B67),0)) | L67: =IFERROR(H67*K67,0)

Sheet PRODUCTOS
A1: 🛍️ PRODUCTOS que fabricás
A2: Anotá acá cada producto que hacés. En la hoja RECETAS decís qué insumos lleva cada uno.
A4: Código | B4: Nombre del producto | C4: Total producido | D4: Notas
A5: P001 | B5: Libreta A6 - 50 Hojas | C5: 0
A6: P002 | B6: Libreta A6 - Solapa | C6: 0
A7: P003 | B7: A5 discos - 100 Hojas | C7: =IFERROR(SUMIFS(PRODUCCION!C:C,PRODUCCION!B:B,B7),0)
A8: P004 | B8: A5 discos - 150 Hojas | C8: =IFERROR(SUMIFS(PRODUCCION!C:C,PRODUCCION!B:B,B8),0)
A9: P005 | B9: B5 discos - 100 Hojas | C9: =IFERROR(SUMIFS(PRODUCCION!C:C,PRODUCCION!B:B,B9),0)
A10: P006 | B10: B5 discos - 150 Hojas | C10: =IFERROR(SUMIFS(PRODUCCION!C:C,PRODUCCION!B:B,B10),0)
A11: P007 | B11: A5 Espiral blando - 80 hojas | C11: =IFERROR(SUMIFS(PRODUCCION!C:C,PRODUCCION!B:B,B11),0)
A12: P008 | B12: B5 Espiral blando - 80 hojas | C12: =IFERROR(SUMIFS(PRODUCCION!C:C,PRODUCCION!B:B,B12),0)
A13: P009 | B13: A5 Espiral Tapa dura - 80 hojas | C13: =IFERROR(SUMIFS(PRODUCCION!C:C,PRODUCCION!B:B,B13),0)
A14: P010 | B14: B5 Espiral Tapa dura - 80 hojas | C14: =IFERROR(SUMIFS(PRODUCCION!C:C,PRODUCCION!B:B,B14),0)
A15: P011 | B15: A5 anillos - 50 hojas | C15: =IFERROR(SUMIFS(PRODUCCION!C:C,PRODUCCION!B:B,B15),0)
A16: P012 | B16: B5 Anillos - 50 hojas | C16: =IFERROR(SUMIFS(PRODUCCION!C:C,PRODUCCION!B:B,B16),0)
A17: P013 | B17: A5 anillos - 100 hojas | C17: =IFERROR(SUMIFS(PRODUCCION!C:C,PRODUCCION!B:B,B17),0)
A18: P014 | B18: B5 Anillos - 100 hojas | C18: =IFERROR(SUMIFS(PRODUCCION!C:C,PRODUCCION!B:B,B18),0)
... A25: P021 | B25: Pack Stickers Suelto | C25: =IFERROR(SUMIFS(PRODUCCION!C:C,PRODUCCION!B:B,B25),0)
C26: =IFERROR(SUMIFS(PRODUCCION!C:C,PRODUCCION!B:B,B26),0)
C27: =IFERROR(SUMIFS(PRODUCCION!C:C,PRODUCCION!B:B,B27),0)
C28: =IFERROR(SUMIFS(PRODUCCION!C:C,PRODUCCION!B:B,B28),0)
C29: =IFERROR(SUMIFS(PRODUCCION!C:C,PRODUCCION!B:B,B29),0)
C30: =IFERROR(SUMIFS(PRODUCCION!C:C,PRODUCCION!B:B,B30),0)
C31: =IFERROR(SUMIFS(PRODUCCION!C:C,PRODUCCION!B:B,B31),0)
C32: =IFERROR(SUMIFS(PRODUCCION!C:C,PRODUCCION!B:B,B32),0)
C33: =IFERROR(SUMIFS(PRODUCCION!C:C,PRODUCCION!B:B,B33),0)
C34: =IFERROR(SUMIFS(PRODUCCION!C:C,PRODUCCION!B:B,B34),0)
C35: =IFERROR(SUMIFS(PRODUCCION!C:C,PRODUCCION!B:B,B35),0)
C36: =IFERROR(SUMIFS(PRODUCCION!C:C,PRODUCCION!B:B,B36),0)
C37: =IFERROR(SUMIFS(PRODUCCION!C:C,PRODUCCION!B:B,B37),0)
... C104: =IFERROR(SUMIFS(PRODUCCION!C:C,PRODUCCION!B:B,B104),0)

Sheet RECETAS
A1: 📋 RECETAS - qué insumos lleva cada producto
A2: Una fila por cada insumo del producto. Ejemplo: Libreta A5 40 hojas usa 40 hojas de bond + 2 tapas de cartón + 1 argolla.
A4: Producto | B4: Insumo | C4: Cantidad por 1 producto | D4: Total producido | E4: Total consumido | F4: Costo en el producto
A5: Libreta A6 - 50 Hojas | B5: Papel foto adhesivo brillo | C5: 1 | D5: =IF(A5="","",IFERROR(SUMIFS(PRODUCCION!C:C,PRODUCCION!B:B,A5),0)) | E5: =IFERROR(C5*D5,0) | F5: =IF(OR($A5="",$B5=""),"",IFERROR($C5*INDEX(INSUMOS!$K$5:$K$67,MATCH($B5,INSUMOS!$B$5:$B$67,0)),0))
A6: Libreta A6 - 50 Hojas | B6: Laminado en frío A4 matte | C6: 1 | D6: =IF(A6="","",IFERROR(SUMIFS(PRODUCCION!C:C,PRODUCCION!B:B,A6),0)) | E6: =IFERROR(C6*D6,0) | F6: =IF(OR($A6="",$B6=""),"",IFERROR($C6*INDEX(INSUMOS!$K$5:$K$67,MATCH($B6,INSUMOS!$B$5:$B$67,0)),0))
A7: Libreta A6 - 50 Hojas | B7: Papel foto adhesivo matte | C7: 0.5 | D7: =IF(A7="","",IFERROR(SUMIFS(PRODUCCION!C:C,PRODUCCION!B:B,A7),0)) | E7: =IFERROR(C7*D7,0) | F7: =IF(OR($A7="",$B7=""),"",IFERROR($C7*INDEX(INSUMOS!$K$5:$K$67,MATCH($B7,INSUMOS!$B$5:$B$67,0)),0))
A8: Libreta A6 - 50 Hojas | B8: Cartón piedra A6 | C8: 2 | D8: =IF(A8="","",IFERROR(SUMIFS(PRODUCCION!C:C,PRODUCCION!B:B,A8),0)) | E8: =IFERROR(C8*D8,0) | F8: =IF(OR($A8="",$B8=""),"",IFERROR($C8*INDEX(INSUMOS!$K$5:$K$67,MATCH($B8,INSUMOS!$B$5:$B$67,0)),0))
A9: Libreta A6 - 50 Hojas | B9: Papel bond A6 105 gr | C9: 50 | D9: =IF(A9="","",IFERROR(SUMIFS(PRODUCCION!C:C,PRODUCCION!B:B,A9),0)) | E9: =IFERROR(C9*D9,0) | F9: =IF(OR($A9="",$B9=""),"",IFERROR($C9*INDEX(INSUMOS!$K$5:$K$67,MATCH($B9,INSUMOS!$B$5:$B$67,0)),0))
A10: Libreta A6 - 50 Hojas | B10: Ojetillos | C10: 2 | D10: =IF(A10="","",IFERROR(SUMIFS(PRODUCCION!C:C,PRODUCCION!B:B,A10),0)) | E10: =IFERROR(C10*D10,0) | F10: =IF(OR($A10="",$B10=""),"",IFERROR($C10*INDEX(INSUMOS!$K$5:$K$67,MATCH($B10,INSUMOS!$B$5:$B$67,0)),0))
A11: Libreta A6 - 50 Hojas | B11: Elásticos | C11: 0.5 | D11: =IF(A11="","",IFERROR(SUMIFS(PRODUCCION!C:C,PRODUCCION!B:B,A11),0)) | E11: =IFERROR(C11*D11,0) | F11: =IF(OR($A11="",$B11=""),"",IFERROR($C11*INDEX(INSUMOS!$K$5:$K$67,MATCH($B11,INSUMOS!$B$5:$B$67,0)),0))
A12: Libreta A6 - 50 Hojas | B12: Anillos 16 mm (5/8") | C12: 7 | D12: =IF(A12="","",IFERROR(SUMIFS(PRODUCCION!C:C,PRODUCCION!B:B,A12),0)) | E12: =IFERROR(C12*D12,0) | F12: =IF(OR($A12="",$B12=""),"",IFERROR($C12*INDEX(INSUMOS!$K$5:$K$67,MATCH($B12,INSUMOS!$B$5:$B$67,0)),0))
A13: Libreta A6 - Solapa | B13: Papel foto adhesivo brillo | C13: 2.2 | D13: =IF(A13="","",IFERROR(SUMIFS(PRODUCCION!C:C,PRODUCCION!B:B,A13),0)) | E13: =IFERROR(C13*D13,0) | F13: =IF(OR($A13="",$B13=""),"",IFERROR($C13*INDEX(INSUMOS!$K$5:$K$67,MATCH($B13,INSUMOS!$B$5:$B$67,0)),0))
A14: Libreta A6 - Solapa | B14: Laminado en frío A4 matte | C14: 2.2 | D14: =IF(A14="","",IFERROR(SUMIFS(PRODUCCION!C:C,PRODUCCION!B:B,A14),0)) | E14: =IFERROR(C14*D14,0) | F14: =IF(OR($A14="",$B14=""),"",IFERROR($C14*INDEX(INSUMOS!$K$5:$K$67,MATCH($B14,INSUMOS!$B$5:$B$67,0)),0))
A15: Libreta A6 - Solapa | B15: Cartón piedra A6 | C15: 2.4 | D15: =IF(A15="","",IFERROR(SUMIFS(PRODUCCION!C:C,PRODUCCION!B:B,A15),0)) | E15: =IFERROR(C15*D15,0) | F15: =IF(OR($A15="",$B15=""),"",IFERROR($C15*INDEX(INSUMOS!$K$5:$K$67,MATCH($B15,INSUMOS!$B$5:$B$67,0)),0))
A16: Libreta A6 - Solapa | B16: Velcro adhesivo | C16: 2 | D16: =IF(A16="","",IFERROR(SUMIFS(PRODUCCION!C:C,PRODUCCION!B:B,A16),0)) | E16: =IFERROR(C16*D16,0) | F16: =IF(OR($A16="",$B16=""),"",IFERROR($C16*INDEX(INSUMOS!$K$5:$K$67,MATCH($B16,INSUMOS!$B$5:$B$67,0)),0))
... A104: Pack Stickers Suelto | B104: Opalina A4 | C104: 0.2 | D104: =IF(A104="","",IFERROR(SUMIFS(PRODUCCION!C:C,PRODUCCION!B:B,A104),0)) | E104: =IFERROR(C104*D104,0) | F104: =IF(OR($A104="",$B104=""),"",IFERROR($C104*INDEX(INSUMOS!$K$5:$K$67,MATCH($B104,INSUMOS!$B$5:$B$67,0)),0))
A105: Pack Stickers Suelto | B105: Bolsa celofán marcapáginas | D105: =IF(A105="","",IFERROR(SUMIFS(PRODUCCION!C:C,PRODUCCION!B:B,A105),0)) | E105: =IFERROR(C105*D105,0) | F105: =IF(OR($A105="",$B105=""),"",IFERROR($C105*INDEX(INSUMOS!$K$5:$K$67,MATCH($B105,INSUMOS!$B$5:$B$67,0)),0))
D106: =IF(A106="","",IFERROR(SUMIFS(PRODUCCION!C:C,PRODUCCION!B:B,A106),0)) | E106: =IFERROR(C106*D106,0) | F106: =IF(OR($A106="",$B106=""),"",IFERROR($C106*INDEX(INSUMOS!$K$5:$K$67,MATCH($B106,INSUMOS!$B$5:$B$67,0)),0))
D107: =IF(A107="","",IFERROR(SUMIFS(PRODUCCION!C:C,PRODUCCION!B:B,A107),0)) | E107: =IFERROR(C107*D107,0) | F107: =IF(OR($A107="",$B107=""),"",IFERROR($C107*INDEX(INSUMOS!$K$5:$K$67,MATCH($B107,INSUMOS!$B$5:$B$67,0)),0))
D108: =IF(A108="","",IFERROR(SUMIFS(PRODUCCION!C:C,PRODUCCION!B:B,A108),0)) | E108: =IFERROR(C108*D108,0) | F108: =IF(OR($A108="",$B108=""),"",IFERROR($C108*INDEX(INSUMOS!$K$5:$K$67,MATCH($B108,INSUMOS!$B$5:$B$67,0)),0))
D109: =IF(A109="","",IFERROR(SUMIFS(PRODUCCION!C:C,PRODUCCION!B:B,A109),0)) | E109: =IFERROR(C109*D109,0) | F109: =IF(OR($A109="",$B109=""),"",IFERROR($C109*INDEX(INSUMOS!$K$5:$K$67,MATCH($B109,INSUMOS!$B$5:$B$67,0)),0))
D110: =IF(A110="","",IFERROR(SUMIFS(PRODUCCION!C:C,PRODUCCION!B:B,A110),0)) | E110: =IFERROR(C110*D110,0) | F110: =IF(OR($A110="",$B110=""),"",IFERROR($C110*INDEX(INSUMOS!$K$5:$K$67,MATCH($B110,INSUMOS!$B$5:$B$67,0)),0))
D111: =IF(A111="","",IFERROR(SUMIFS(PRODUCCION!C:C,PRODUCCION!B:B,A111),0)) | E111: =IFERROR(C111*D111,0) | F111: =IF(OR($A111="",$B111=""),"",IFERROR($C111*INDEX(INSUMOS!$K$5:$K$67,MATCH($B111,INSUMOS!$B$5:$B$67,0)),0))
D112: =IF(A112="","",IFERROR(SUMIFS(PRODUCCION!C:C,PRODUCCION!B:B,A112),0)) | E112: =IFERROR(C112*D112,0) | F112: =IF(OR($A112="",$B112=""),"",IFERROR($C112*INDEX(INSUMOS!$K$5:$K$67,MATCH($B112,INSUMOS!$B$5:$B$67,0)),0))
D113: =IF(A113="","",IFERROR(SUMIFS(PRODUCCION!C:C,PRODUCCION!B:B,A113),0)) | E113: =IFERROR(C113*D113,0) | F113: =IF(OR($A113="",$B113=""),"",IFERROR($C113*INDEX(INSUMOS!$K$5:$K$67,MATCH($B113,INSUMOS!$B$5:$B$67,0)),0))
D114: =IF(A114="","",IFERROR(SUMIFS(PRODUCCION!C:C,PRODUCCION!B:B,A114),0)) | E114: =IFERROR(C114*D114,0) | F114: =IF(OR($A114="",$B114=""),"",IFERROR($C114*INDEX(INSUMOS!$K$5:$K$67,MATCH($B114,INSUMOS!$B$5:$B$67,0)),0))
D115: =IF(A115="","",IFERROR(SUMIFS(PRODUCCION!C:C,PRODUCCION!B:B,A115),0)) | E115: =IFERROR(C115*D115,0) | F115: =IF(OR($A115="",$B115=""),"",IFERROR($C115*INDEX(INSUMOS!$K$5:$K$67,MATCH($B115,INSUMOS!$B$5:$B$67,0)),0))
D116: =IF(A116="","",IFERROR(SUMIFS(PRODUCCION!C:C,PRODUCCION!B:B,A116),0)) | E116: =IFERROR(C116*D116,0) | F116: =IF(OR($A116="",$B116=""),"",IFERROR($C116*INDEX(INSUMOS!$K$5:$K$67,MATCH($B116,INSUMOS!$B$5:$B$67,0)),0))
D117: =IF(A117="","",IFERROR(SUMIFS(PRODUCCION!C:C,PRODUCCION!B:B,A117),0)) | E117: =IFERROR(C117*D117,0) | F117: =IF(OR($A117="",$B117=""),"",IFERROR($C117*INDEX(INSUMOS!$K$5:$K$67,MATCH($B117,INSUMOS!$B$5:$B$67,0)),0))
... D504: =IF(A504="","",IFERROR(SUMIFS(PRODUCCION!C:C,PRODUCCION!B:B,A504),0)) | E504: =IFERROR(C504*D504,0) | F504: =IF(OR($A504="",$B504=""),"",IFERROR($C504*INDEX(INSUMOS!$K$5:$K$67,MATCH($B504,INSUMOS!$B$5:$B$67,0)),0))

Sheet COMPRAS
A1: 🛒 COMPRAS - registro de entradas de insumo
A2: Cada vez que compres, anotá acá (con el costo total). El stock sube solo y, si pagaste más caro que antes, el precio del insumo se actualiza solo (si baja, no se toca).
A4: Fecha | B4: Insumo | C4: Cantidad | D4: Costo total (opcional) | E4: Notas | F4: Precio unitario
F5: =IF(OR(B5="",C5="",D5="",C5=0),"",D5/C5)
F6: =IF(OR(B6="",C6="",D6="",C6=0),"",D6/C6)
F7: =IF(OR(B7="",C7="",D7="",C7=0),"",D7/C7)
F8: =IF(OR(B8="",C8="",D8="",C8=0),"",D8/C8)
F9: =IF(OR(B9="",C9="",D9="",C9=0),"",D9/C9)
F10: =IF(OR(B10="",C10="",D10="",C10=0),"",D10/C10)
F11: =IF(OR(B11="",C11="",D11="",C11=0),"",D11/C11)
F12: =IF(OR(B12="",C12="",D12="",C12=0),"",D12/C12)
F13: =IF(OR(B13="",C13="",D13="",C13=0),"",D13/C13)
F14: =IF(OR(B14="",C14="",D14="",C14=0),"",D14/C14)
F15: =IF(OR(B15="",C15="",D15="",C15=0),"",D15/C15)
F16: =IF(OR(B16="",C16="",D16="",C16=0),"",D16/C16)
... F504: =IF(OR(B504="",C504="",D504="",C504=0),"",D504/C504)

Sheet PERDIDAS
A1: ⚠️ PÉRDIDAS - insumos dañados, mal impresos o extraviados
A2: Si te equivocás o se daña un insumo, anotalo acá. El stock actual en INSUMOS se descuenta solo y ves cuánta plata perdiste.
A4: Fecha | B4: Insumo | C4: Cantidad perdida | D4: Motivo | E4: Costo perdido | F4: Notas
E5: =IF(OR(B5="",C5=""),"",IFERROR(C5*INDEX(INSUMOS!$K$5:$K$67,MATCH(B5,INSUMOS!$B$5:$B$67,0)),""))
E6: =IF(OR(B6="",C6=""),"",IFERROR(C6*INDEX(INSUMOS!$K$5:$K$67,MATCH(B6,INSUMOS!$B$5:$B$67,0)),""))
E7: =IF(OR(B7="",C7=""),"",IFERROR(C7*INDEX(INSUMOS!$K$5:$K$67,MATCH(B7,INSUMOS!$B$5:$B$67,0)),""))
E8: =IF(OR(B8="",C8=""),"",IFERROR(C8*INDEX(INSUMOS!$K$5:$K$67,MATCH(B8,INSUMOS!$B$5:$B$67,0)),""))
E9: =IF(OR(B9="",C9=""),"",IFERROR(C9*INDEX(INSUMOS!$K$5:$K$67,MATCH(B9,INSUMOS!$B$5:$B$67,0)),""))
E10: =IF(OR(B10="",C10=""),"",IFERROR(C10*INDEX(INSUMOS!$K$5:$K$67,MATCH(B10,INSUMOS!$B$5:$B$67,0)),""))
E11: =IF(OR(B11="",C11=""),"",IFERROR(C11*INDEX(INSUMOS!$K$5:$K$67,MATCH(B11,INSUMOS!$B$5:$B$67,0)),""))
E12: =IF(OR(B12="",C12=""),"",IFERROR(C12*INDEX(INSUMOS!$K$5:$K$67,MATCH(B12,INSUMOS!$B$5:$B$67,0)),""))
E13: =IF(OR(B13="",C13=""),"",IFERROR(C13*INDEX(INSUMOS!$K$5:$K$67,MATCH(B13,INSUMOS!$B$5:$B$67,0)),""))
E14: =IF(OR(B14="",C14=""),"",IFERROR(C14*INDEX(INSUMOS!$K$5:$K$67,MATCH(B14,INSUMOS!$B$5:$B$67,0)),""))
E15: =IF(OR(B15="",C15=""),"",IFERROR(C15*INDEX(INSUMOS!$K$5:$K$67,MATCH(B15,INSUMOS!$B$5:$B$67,0)),""))
E16: =IF(OR(B16="",C16=""),"",IFERROR(C16*INDEX(INSUMOS!$K$5:$K$67,MATCH(B16,INSUMOS!$B$5:$B$67,0)),""))
... E504: =IF(OR(B504="",C504=""),"",IFERROR(C504*INDEX(INSUMOS!$K$5:$K$67,MATCH(B504,INSUMOS!$B$5:$B$67,0)),""))

Sheet PRODUCCION
A1: 🏭 PRODUCCIÓN - registro de productos fabricados
A2: Cada vez que hacés productos, anotá cuántos. Los insumos se descuentan solos del stock según la receta.
A4: Fecha | B4: Producto | C4: Cantidad fabricada | D4: Notas

Sheet COSTOS
A1: 💰 COSTOS - cuánto te cuesta fabricar cada producto
A2: EJEMPLO con la Libreta A6 - 50 Hojas: elegí el producto en la celda amarilla, listá sus insumos y todo lo demás se calcula solo (cantidad desde RECETAS, costo desde INSUMOS). Copiá el bloque más abajo para tus otros productos.
A4: Producto: | B4: Libreta A6 - 50 Hojas
A6: Insumo | B6: Cantidad por unidad | C6: Costo unitario | D6: Subtotal
A7: Papel foto adhesivo brillo | B7: =IF($A7="","",IFERROR(SUMIFS(RECETAS!$C:$C,RECETAS!$A:$A,$B$4,RECETAS!$B:$B,$A7),"")) | C7: =IF($A7="","",IFERROR(INDEX(INSUMOS!$K$5:$K$67,MATCH($A7,INSUMOS!$B$5:$B$67,0)),0)) | D7: =IF($A7="","",IFERROR(B7*C7,0))
A8: Laminado en frío A4 matte | B8: =IF($A8="","",IFERROR(SUMIFS(RECETAS!$C:$C,RECETAS!$A:$A,$B$4,RECETAS!$B:$B,$A8),"")) | C8: =IF($A8="","",IFERROR(INDEX(INSUMOS!$K$5:$K$67,MATCH($A8,INSUMOS!$B$5:$B$67,0)),0)) | D8: =IF($A8="","",IFERROR(B8*C8,0))
A9: Papel foto adhesivo matte | B9: =IF($A9="","",IFERROR(SUMIFS(RECETAS!$C:$C,RECETAS!$A:$A,$B$4,RECETAS!$B:$B,$A9),"")) | C9: =IF($A9="","",IFERROR(INDEX(INSUMOS!$K$5:$K$67,MATCH($A9,INSUMOS!$B$5:$B$67,0)),0)) | D9: =IF($A9="","",IFERROR(B9*C9,0))
A10: Cartón piedra A6 | B10: =IF($A10="","",IFERROR(SUMIFS(RECETAS!$C:$C,RECETAS!$A:$A,$B$4,RECETAS!$B:$B,$A10),"")) | C10: =IF($A10="","",IFERROR(INDEX(INSUMOS!$K$5:$K$67,MATCH($A10,INSUMOS!$B$5:$B$67,0)),0)) | D10: =IF($A10="","",IFERROR(B10*C10,0))
A11: Papel bond A6 105 gr | B11: =IF($A11="","",IFERROR(SUMIFS(RECETAS!$C:$C,RECETAS!$A:$A,$B$4,RECETAS!$B:$B,$A11),"")) | C11: =IF($A11="","",IFERROR(INDEX(INSUMOS!$K$5:$K$67,MATCH($A11,INSUMOS!$B$5:$B$67,0)),0)) | D11: =IF($A11="","",IFERROR(B11*C11,0))
A12: Ojetillos | B12: =IF($A12="","",IFERROR(SUMIFS(RECETAS!$C:$C,RECETAS!$A:$A,$B$4,RECETAS!$B:$B,$A12),"")) | C12: =IF($A12="","",IFERROR(INDEX(INSUMOS!$K$5:$K$67,MATCH($A12,INSUMOS!$B$5:$B$67,0)),0)) | D12: =IF($A12="","",IFERROR(B12*C12,0))
A13: Elásticos | B13: =IF($A13="","",IFERROR(SUMIFS(RECETAS!$C:$C,RECETAS!$A:$A,$B$4,RECETAS!$B:$B,$A13),"")) | C13: =IF($A13="","",IFERROR(INDEX(INSUMOS!$K$5:$K$67,MATCH($A13,INSUMOS!$B$5:$B$67,0)),0)) | D13: =IF($A13="","",IFERROR(B13*C13,0))
A14: Anillos 16 mm (5/8") | B14: =IF($A14="","",IFERROR(SUMIFS(RECETAS!$C:$C,RECETAS!$A:$A,$B$4,RECETAS!$B:$B,$A14),"")) | C14: =IF($A14="","",IFERROR(INDEX(INSUMOS!$K$5:$K$67,MATCH($A14,INSUMOS!$B$5:$B$67,0)),0)) | D14: =IF($A14="","",IFERROR(B14*C14,0))
B15: =IF($A15="","",IFERROR(SUMIFS(RECETAS!$C:$C,RECETAS!$A:$A,$B$4,RECETAS!$B:$B,$A15),"")) | C15: =IF($A15="","",IFERROR(INDEX(INSUMOS!$K$5:$K$67,MATCH($A15,INSUMOS!$B$5:$B$67,0)),0)) | D15: =IF($A15="","",IFERROR(B15*C15,0))
B16: =IF($A16="","",IFERROR(SUMIFS(RECETAS!$C:$C,RECETAS!$A:$A,$B$4,RECETAS!$B:$B,$A16),"")) | C16: =IF($A16="","",IFERROR(INDEX(INSUMOS!$K$5:$K$67,MATCH($A16,INSUMOS!$B$5:$B$67,0)),0)) | D16: =IF($A16="","",IFERROR(B16*C16,0))
A18: Costo de insumos | D18: =SUM(D7:D16)
A19: Otros costos por unidad (tinta, luz, mano de obra…) | D19: 0
A20: COSTO TOTAL por unidad | D20: =D18+D19
A21: Multiplicador de venta (ej: 2,5 = cobrar 2,5 veces el costo) | D21: 2.5
A22: PRECIO SUGERIDO | D22: =IFERROR(ROUND(D20*D21,0),0)
A24: 👇 Para otro producto: seleccioná A4:D22, copiá y pegá acá abajo, cambiá el producto y los insumos.

Sheet PRECIOS
A1: 🏷️ PRECIOS - costo, precio de venta, IVA y ganancia por producto
A2: Los productos y su costo de insumos se traen solos (si sube el precio de un insumo, el costo sube solo). Vos llenás lo amarillo: otros costos y el precio de venta (con IVA incluido).
A3: IVA aplicado (editable) → | B3: 0.19
A4: Producto | B4: Costo insumos | C4: Otros costos | D4: Costo total | E4: Precio de venta (c/IVA) | F4: IVA incluido | G4: Precio neto (sin IVA) | H4: Ganancia por unidad | I4: Margen % | J4: Notas
A5: =IF(PRODUCTOS!B5="","",PRODUCTOS!B5) | B5: =IF($A5="","",SUMIFS(RECETAS!$F:$F,RECETAS!$A:$A,$A5)) | D5: =IF($A5="","",B5+IF(C5="",0,C5)) | E5: 5000 | F5: =IF(OR($A5="",$E5=""),"",ROUND($E5-$E5/(1+$B$3),0)) | G5: =IF(OR($A5="",$E5=""),"",ROUND($E5/(1+$B$3),0)) | H5: =IF(OR($A5="",$E5=""),"",G5-D5) | I5: =IF(OR($A5="",$E5="",$E5=0),"",H5/G5) | J5: EJEMPLO: borrá este precio y poné el tuyo.
A6: =IF(PRODUCTOS!B6="","",PRODUCTOS!B6) | B6: =IF($A6="","",SUMIFS(RECETAS!$F:$F,RECETAS!$A:$A,$A6)) | D6: =IF($A6="","",B6+IF(C6="",0,C6)) | F6: =IF(OR($A6="",$E6=""),"",ROUND($E6-$E6/(1+$B$3),0)) | G6: =IF(OR($A6="",$E6=""),"",ROUND($E6/(1+$B$3),0)) | H6: =IF(OR($A6="",$E6=""),"",G6-D6) | I6: =IF(OR($A6="",$E6="",$E6=0),"",H6/G6)
A7: =IF(PRODUCTOS!B7="","",PRODUCTOS!B7) | B7: =IF($A7="","",SUMIFS(RECETAS!$F:$F,RECETAS!$A:$A,$A7)) | D7: =IF($A7="","",B7+IF(C7="",0,C7)) | F7: =IF(OR($A7="",$E7=""),"",ROUND($E7-$E7/(1+$B$3),0)) | G7: =IF(OR($A7="",$E7=""),"",ROUND($E7/(1+$B$3),0)) | H7: =IF(OR($A7="",$E7=""),"",G7-D7) | I7: =IF(OR($A7="",$E7="",$E7=0),"",H7/G7)
A8: =IF(PRODUCTOS!B8="","",PRODUCTOS!B8) | B8: =IF($A8="","",SUMIFS(RECETAS!$F:$F,RECETAS!$A:$A,$A8)) | D8: =IF($A8="","",B8+IF(C8="",0,C8)) | F8: =IF(OR($A8="",$E8=""),"",ROUND($E8-$E8/(1+$B$3),0)) | G8: =IF(OR($A8="",$E8=""),"",ROUND($E8/(1+$B$3),0)) | H8: =IF(OR($A8="",$E8=""),"",G8-D8) | I8: =IF(OR($A8="",$E8="",$E8=0),"",H8/G8)
A9: =IF(PRODUCTOS!B9="","",PRODUCTOS!B9) | B9: =IF($A9="","",SUMIFS(RECETAS!$F:$F,RECETAS!$A:$A,$A9)) | D9: =IF($A9="","",B9+IF(C9="",0,C9)) | F9: =IF(OR($A9="",$E9=""),"",ROUND($E9-$E9/(1+$B$3),0)) | G9: =IF(OR($A9="",$E9=""),"",ROUND($E9/(1+$B$3),0)) | H9: =IF(OR($A9="",$E9=""),"",G9-D9) | I9: =IF(OR($A9="",$E9="",$E9=0),"",H9/G9)
A10: =IF(PRODUCTOS!B10="","",PRODUCTOS!B10) | B10: =IF($A10="","",SUMIFS(RECETAS!$F:$F,RECETAS!$A:$A,$A10)) | D10: =IF($A10="","",B10+IF(C10="",0,C10)) | F10: =IF(OR($A10="",$E10=""),"",ROUND($E10-$E10/(1+$B$3),0)) | G10: =IF(OR($A10="",$E10=""),"",ROUND($E10/(1+$B$3),0)) | H10: =IF(OR($A10="",$E10=""),"",G10-D10) | I10: =IF(OR($A10="",$E10="",$E10=0),"",H10/G10)
A11: =IF(PRODUCTOS!B11="","",PRODUCTOS!B11) | B11: =IF($A11="","",SUMIFS(RECETAS!$F:$F,RECETAS!$A:$A,$A11)) | D11: =IF($A11="","",B11+IF(C11="",0,C11)) | F11: =IF(OR($A11="",$E11=""),"",ROUND($E11-$E11/(1+$B$3),0)) | G11: =IF(OR($A11="",$E11=""),"",ROUND($E11/(1+$B$3),0)) | H11: =IF(OR($A11="",$E11=""),"",G11-D11) | I11: =IF(OR($A11="",$E11="",$E11=0),"",H11/G11)
A12: =IF(PRODUCTOS!B12="","",PRODUCTOS!B12) | B12: =IF($A12="","",SUMIFS(RECETAS!$F:$F,RECETAS!$A:$A,$A12)) | D12: =IF($A12="","",B12+IF(C12="",0,C12)) | F12: =IF(OR($A12="",$E12=""),"",ROUND($E12-$E12/(1+$B$3),0)) | G12: =IF(OR($A12="",$E12=""),"",ROUND($E12/(1+$B$3),0)) | H12: =IF(OR($A12="",$E12=""),"",G12-D12) | I12: =IF(OR($A12="",$E12="",$E12=0),"",H12/G12)
A13: =IF(PRODUCTOS!B13="","",PRODUCTOS!B13) | B13: =IF($A13="","",SUMIFS(RECETAS!$F:$F,RECETAS!$A:$A,$A13)) | D13: =IF($A13="","",B13+IF(C13="",0,C13)) | F13: =IF(OR($A13="",$E13=""),"",ROUND($E13-$E13/(1+$B$3),0)) | G13: =IF(OR($A13="",$E13=""),"",ROUND($E13/(1+$B$3),0)) | H13: =IF(OR($A13="",$E13=""),"",G13-D13) | I13: =IF(OR($A13="",$E13="",$E13=0),"",H13/G13)
A14: =IF(PRODUCTOS!B14="","",PRODUCTOS!B14) | B14: =IF($A14="","",SUMIFS(RECETAS!$F:$F,RECETAS!$A:$A,$A14)) | D14: =IF($A14="","",B14+IF(C14="",0,C14)) | F14: =IF(OR($A14="",$E14=""),"",ROUND($E14-$E14/(1+$B$3),0)) | G14: =IF(OR($A14="",$E14=""),"",ROUND($E14/(1+$B$3),0)) | H14: =IF(OR($A14="",$E14=""),"",G14-D14) | I14: =IF(OR($A14="",$E14="",$E14=0),"",H14/G14)
A15: =IF(PRODUCTOS!B15="","",PRODUCTOS!B15) | B15: =IF($A15="","",SUMIFS(RECETAS!$F:$F,RECETAS!$A:$A,$A15)) | D15: =IF($A15="","",B15+IF(C15="",0,C15)) | F15: =IF(OR($A15="",$E15=""),"",ROUND($E15-$E15/(1+$B$3),0)) | G15: =IF(OR($A15="",$E15=""),"",ROUND($E15/(1+$B$3),0)) | H15: =IF(OR($A15="",$E15=""),"",G15-D15) | I15: =IF(OR($A15="",$E15="",$E15=0),"",H15/G15)
A16: =IF(PRODUCTOS!B16="","",PRODUCTOS!B16) | B16: =IF($A16="","",SUMIFS(RECETAS!$F:$F,RECETAS!$A:$A,$A16)) | D16: =IF($A16="","",B16+IF(C16="",0,C16)) | F16: =IF(OR($A16="",$E16=""),"",ROUND($E16-$E16/(1+$B$3),0)) | G16: =IF(OR($A16="",$E16=""),"",ROUND($E16/(1+$B$3),0)) | H16: =IF(OR($A16="",$E16=""),"",G16-D16) | I16: =IF(OR($A16="",$E16="",$E16=0),"",H16/G16)
A17: =IF(PRODUCTOS!B17="","",PRODUCTOS!B17) | B17: =IF($A17="","",SUMIFS(RECETAS!$F:$F,RECETAS!$A:$A,$A17)) | D17: =IF($A17="","",B17+IF(C17="",0,C17)) | F17: =IF(OR($A17="",$E17=""),"",ROUND($E17-$E17/(1+$B$3),0)) | G17: =IF(OR($A17="",$E17=""),"",ROUND($E17/(1+$B$3),0)) | H17: =IF(OR($A17="",$E17=""),"",G17-D17) | I17: =IF(OR($A17="",$E17="",$E17=0),"",H17/G17)
... A104: =IF(PRODUCTOS!B104="","",PRODUCTOS!B104) | B104: =IF($A104="","",SUMIFS(RECETAS!$F:$F,RECETAS!$A:$A,$A104)) | D104: =IF($A104="","",B104+IF(C104="",0,C104)) | F104: =IF(OR($A104="",$E104=""),"",ROUND($E104-$E104/(1+$B$3),0)) | G104: =IF(OR($A104="",$E104=""),"",ROUND($E104/(1+$B$3),0)) | H104: =IF(OR($A104="",$E104=""),"",G104-D104) | I104: =IF(OR($A104="",$E104="",$E104=0),"",H104/G104)
